<?xml version="1.0" encoding="utf-8"?>
<!-- Created by Gilgamesch on 9/8/2013 3:05:32 PM -->
<GameData>
	<!--/////////Civilization_BuildingClassOverrides\\\\\\\\\-->
  
<Civilization_BuildingClassOverrides>
	<!--/////////Civilization_BuildingClassOverrides\\\\\\\\\-->
    <!--/////////Unique Buildingss\\\\\\\\\-->
	<Row>
		<CivilizationType>CIVILIZATION_POLYNESIA</CivilizationType>
		<BuildingClassType>BUILDINGCLASS_WALLS</BuildingClassType>
		<BuildingType>BUILDING_CCTPUNIQUE1</BuildingType>
	</Row>
	<Row>
		<CivilizationType>CIVILIZATION_BRAZIL</CivilizationType>
		<BuildingClassType>BUILDINGCLASS_WALLS</BuildingClassType>
		<BuildingType>BUILDING_CCTPUNIQUE2</BuildingType>
	</Row>
		<Row>
		<CivilizationType>CIVILIZATION_FRANCE</CivilizationType>
		<BuildingClassType>BUILDINGCLASS_WALLS</BuildingClassType>
		<BuildingType>BUILDING_CCTPUNIQUE3</BuildingType>
	</Row>
	<Row>
		<CivilizationType>CIVILIZATION_MOROCCO</CivilizationType>
		<BuildingClassType>BUILDINGCLASS_WALLS</BuildingClassType>
		<BuildingType>BUILDING_CCTPUNIQUE4</BuildingType>
	</Row>
	<Row>
		<CivilizationType>CIVILIZATION_PORTUGAL</CivilizationType>
		<BuildingClassType>BUILDINGCLASS_WALLS</BuildingClassType>
		<BuildingType>BUILDING_CCTPUNIQUE5</BuildingType>
	</Row>
	<Row>
		<CivilizationType>CIVILIZATION_NETHERLANDS</CivilizationType>
		<BuildingClassType>BUILDINGCLASS_WALLS</BuildingClassType>
		<BuildingType>BUILDING_CCTPUNIQUE5</BuildingType>
	</Row>
	<Row>
		<CivilizationType>CIVILIZATION_INCA</CivilizationType>
		<BuildingClassType>BUILDINGCLASS_WALLS</BuildingClassType>
		<BuildingType>BUILDING_CCTPUNIQUE5</BuildingType>
	</Row>



	<!--/////////Civilization_BuildingClassOverrides\\\\\\\\\-->
	<Row>
		<CivilizationType>CIVILIZATION_BARBARIAN</CivilizationType>
		<BuildingClassType>BUILDINGCLASS_PRECOG_PROJECT</BuildingClassType>
		<BuildingType/>
	</Row>
	<Row>
		<CivilizationType>CIVILIZATION_MINOR</CivilizationType>
		<BuildingClassType>BUILDINGCLASS_PRECOG_PROJECT</BuildingClassType>
		<BuildingType/>
	</Row>
	<Row>
		<CivilizationType>CIVILIZATION_BARBARIAN</CivilizationType>
		<BuildingClassType>BUILDINGCLASS_MARKOV_ECLIPSE</BuildingClassType>
		<BuildingType/>
	</Row>
	<Row>
		<CivilizationType>CIVILIZATION_MINOR</CivilizationType>
		<BuildingClassType>BUILDINGCLASS_MARKOV_ECLIPSE</BuildingClassType>
		<BuildingType/>
	</Row>
	<Row>
		<CivilizationType>CIVILIZATION_BARBARIAN</CivilizationType>
		<BuildingClassType>BUILDINGCLASS_QUANTUM_TELEPORTER</BuildingClassType>
		<BuildingType/>
	</Row>
	<Row>
		<CivilizationType>CIVILIZATION_MINOR</CivilizationType>
		<BuildingClassType>BUILDINGCLASS_QUANTUM_TELEPORTER</BuildingClassType>
		<BuildingType/>
	</Row>
	<Row>
		<CivilizationType>CIVILIZATION_BARBARIAN</CivilizationType>
		<BuildingClassType>BUILDINGCLASS_CYBORG_FACTORY</BuildingClassType>
		<BuildingType/>
	</Row>
	<Row>
		<CivilizationType>CIVILIZATION_MINOR</CivilizationType>
		<BuildingClassType>BUILDINGCLASS_CYBORG_FACTORY</BuildingClassType>
		<BuildingType/>
	</Row>
	<Row>
		<CivilizationType>CIVILIZATION_BARBARIAN</CivilizationType>
		<BuildingClassType>BUILDINGCLASS_MASTER_CONTROL</BuildingClassType>
		<BuildingType/>
	</Row>
	<Row>
		<CivilizationType>CIVILIZATION_MINOR</CivilizationType>
		<BuildingClassType>BUILDINGCLASS_MASTER_CONTROL</BuildingClassType>
		<BuildingType/>
	</Row>
	<Row>
		<CivilizationType>CIVILIZATION_BARBARIAN</CivilizationType>
		<BuildingClassType>BUILDINGCLASS_RESURRECTION_DEVICE</BuildingClassType>
		<BuildingType/>
	</Row>
	<Row>
		<CivilizationType>CIVILIZATION_MINOR</CivilizationType>
		<BuildingClassType>BUILDINGCLASS_RESURRECTION_DEVICE</BuildingClassType>
		<BuildingType/>
	</Row>
	<Row>
		<CivilizationType>CIVILIZATION_BARBARIAN</CivilizationType>
		<BuildingClassType>BUILDINGCLASS_INDRA</BuildingClassType>
		<BuildingType/>
	</Row>
	<Row>
		<CivilizationType>CIVILIZATION_MINOR</CivilizationType>
		<BuildingClassType>BUILDINGCLASS_INDRA</BuildingClassType>
		<BuildingType/>
	</Row>
	<Row>
		<CivilizationType>CIVILIZATION_BARBARIAN</CivilizationType>
		<BuildingClassType>BUILDINGCLASS_REICHSTAG</BuildingClassType>
		<BuildingType/>
	</Row>
	<Row>
		<CivilizationType>CIVILIZATION_MINOR</CivilizationType>
		<BuildingClassType>BUILDINGCLASS_REICHSTAG</BuildingClassType>
		<BuildingType/>
	</Row>
	<Row>
		<CivilizationType>CIVILIZATION_BARBARIAN</CivilizationType>
		<BuildingClassType>BUILDINGCLASS_CHALL</BuildingClassType>
		<BuildingType/>
	</Row>
	<Row>
		<CivilizationType>CIVILIZATION_MINOR</CivilizationType>
		<BuildingClassType>BUILDINGCLASS_CHALL</BuildingClassType>
		<BuildingType/>
	</Row>
	<Row>
		<CivilizationType>CIVILIZATION_BARBARIAN</CivilizationType>
		<BuildingClassType>BUILDINGCLASS_ANTI</BuildingClassType>
		<BuildingType/>
	</Row>
	<Row>
		<CivilizationType>CIVILIZATION_MINOR</CivilizationType>
		<BuildingClassType>BUILDINGCLASS_ANTI</BuildingClassType>
		<BuildingType/>
	</Row>
	<Row>
		<CivilizationType>CIVILIZATION_BARBARIAN</CivilizationType>
		<BuildingClassType>BUILDINGCLASS_DIONYSUS</BuildingClassType>
		<BuildingType/>
	</Row>
	<Row>
		<CivilizationType>CIVILIZATION_MINOR</CivilizationType>
		<BuildingClassType>BUILDINGCLASS_DIONYSUS</BuildingClassType>
		<BuildingType/>
	</Row>
	<Row>
		<CivilizationType>CIVILIZATION_BARBARIAN</CivilizationType>
		<BuildingClassType>BUILDINGCLASS_OSIRION</BuildingClassType>
		<BuildingType/>
	</Row>
	<Row>
		<CivilizationType>CIVILIZATION_MINOR</CivilizationType>
		<BuildingClassType>BUILDINGCLASS_OSIRION</BuildingClassType>
		<BuildingType/>
	</Row>
	<Row>
		<CivilizationType>CIVILIZATION_BARBARIAN</CivilizationType>
		<BuildingClassType>BUILDINGCLASS_DWARF</BuildingClassType>
		<BuildingType/>
	</Row>
	<Row>
		<CivilizationType>CIVILIZATION_MINOR</CivilizationType>
		<BuildingClassType>BUILDINGCLASS_DWARF</BuildingClassType>
		<BuildingType/>
	</Row>
	<Row>
		<CivilizationType>CIVILIZATION_BARBARIAN</CivilizationType>
		<BuildingClassType>BUILDINGCLASS_CARNAC</BuildingClassType>
		<BuildingType/>
	</Row>
	<Row>
		<CivilizationType>CIVILIZATION_MINOR</CivilizationType>
		<BuildingClassType>BUILDINGCLASS_CARNAC</BuildingClassType>
		<BuildingType/>
	</Row>
	<Row>
		<CivilizationType>CIVILIZATION_BARBARIAN</CivilizationType>
		<BuildingClassType>BUILDINGCLASS_CATAL</BuildingClassType>
		<BuildingType/>
	</Row>
	<Row>
		<CivilizationType>CIVILIZATION_MINOR</CivilizationType>
		<BuildingClassType>BUILDINGCLASS_CATAL</BuildingClassType>
		<BuildingType/>
	</Row>
	<Row>
		<CivilizationType>CIVILIZATION_BARBARIAN</CivilizationType>
		<BuildingClassType>BUILDINGCLASS_ATLIT_YAM</BuildingClassType>
		<BuildingType/>
	</Row>
	<Row>
		<CivilizationType>CIVILIZATION_MINOR</CivilizationType>
		<BuildingClassType>BUILDINGCLASS_ATLIT_YAM</BuildingClassType>
		<BuildingType/>
	</Row>
	<Row>
		<CivilizationType>CIVILIZATION_BARBARIAN</CivilizationType>
		<BuildingClassType>BUILDINGCLASS_NEBRA</BuildingClassType>
		<BuildingType/>
	</Row>
	<Row>
		<CivilizationType>CIVILIZATION_MINOR</CivilizationType>
		<BuildingClassType>BUILDINGCLASS_NEBRA</BuildingClassType>
		<BuildingType/>
	</Row>
	<Row>
		<CivilizationType>CIVILIZATION_BARBARIAN</CivilizationType>
		<BuildingClassType>BUILDINGCLASS_TERRA_COMPUTER</BuildingClassType>
		<BuildingType/>
	</Row>
	<Row>
		<CivilizationType>CIVILIZATION_MINOR</CivilizationType>
		<BuildingClassType>BUILDINGCLASS_TERRA_COMPUTER</BuildingClassType>
		<BuildingType/>
	</Row>
	<Row>
		<CivilizationType>CIVILIZATION_BARBARIAN</CivilizationType>
		<BuildingClassType>BUILDINGCLASS_CLONING_VATS</BuildingClassType>
		<BuildingType/>
	</Row>
	<Row>
		<CivilizationType>CIVILIZATION_MINOR</CivilizationType>
		<BuildingClassType>BUILDINGCLASS_CLONING_VATS</BuildingClassType>
		<BuildingType/>
	</Row>
	<Row>
		<CivilizationType>CIVILIZATION_BARBARIAN</CivilizationType>
		<BuildingClassType>BUILDINGCLASS_CLINICAL_IMMORTALITY</BuildingClassType>
		<BuildingType/>
	</Row>
	<Row>
		<CivilizationType>CIVILIZATION_MINOR</CivilizationType>
		<BuildingClassType>BUILDINGCLASS_CLINICAL_IMMORTALITY</BuildingClassType>
		<BuildingType/>
	</Row>
	<Row>
		<CivilizationType>CIVILIZATION_BARBARIAN</CivilizationType>
		<BuildingClassType>BUILDINGCLASS_BUCKINGHAM</BuildingClassType>
		<BuildingType/>
	</Row>
	<Row>
		<CivilizationType>CIVILIZATION_MINOR</CivilizationType>
		<BuildingClassType>BUILDINGCLASS_BUCKINGHAM</BuildingClassType>
		<BuildingType/>
	</Row>
	<Row>
		<CivilizationType>CIVILIZATION_BARBARIAN</CivilizationType>
		<BuildingClassType>BUILDINGCLASS_THEORY_OF_EVERYTHING</BuildingClassType>
		<BuildingType/>
	</Row>
	<Row>
		<CivilizationType>CIVILIZATION_MINOR</CivilizationType>
		<BuildingClassType>BUILDINGCLASS_THEORY_OF_EVERYTHING</BuildingClassType>
		<BuildingType/>
	</Row>
	<Row>
		<CivilizationType>CIVILIZATION_BARBARIAN</CivilizationType>
		<BuildingClassType>BUILDINGCLASS_NETWORK_BACKBONE</BuildingClassType>
		<BuildingType/>
	</Row>
	<Row>
		<CivilizationType>CIVILIZATION_MINOR</CivilizationType>
		<BuildingClassType>BUILDINGCLASS_NETWORK_BACKBONE</BuildingClassType>
		<BuildingType/>
	</Row>
	<Row>
		<CivilizationType>CIVILIZATION_BARBARIAN</CivilizationType>
		<BuildingClassType>BUILDINGCLASS_MANIFOLD_HARMONICS</BuildingClassType>
		<BuildingType/>
	</Row>
	<Row>
		<CivilizationType>CIVILIZATION_MINOR</CivilizationType>
		<BuildingClassType>BUILDINGCLASS_MANIFOLD_HARMONICS</BuildingClassType>
		<BuildingType/>
	</Row>
	<Row>
		<CivilizationType>CIVILIZATION_BARBARIAN</CivilizationType>
		<BuildingClassType>BUILDINGCLASS_TELEPATHIC_MATRIX</BuildingClassType>
		<BuildingType/>
	</Row>
	<Row>
		<CivilizationType>CIVILIZATION_MINOR</CivilizationType>
		<BuildingClassType>BUILDINGCLASS_TELEPATHIC_MATRIX</BuildingClassType>
		<BuildingType/>
	</Row>
	<Row>
		<CivilizationType>CIVILIZATION_BARBARIAN</CivilizationType>
		<BuildingClassType>BUILDINGCLASS_NEURAL_AMPLIFIER</BuildingClassType>
		<BuildingType/>
	</Row>
	<Row>
		<CivilizationType>CIVILIZATION_MINOR</CivilizationType>
		<BuildingClassType>BUILDINGCLASS_NEURAL_AMPLIFIER</BuildingClassType>
		<BuildingType/>
	</Row>
	<Row>
		<CivilizationType>CIVILIZATION_BARBARIAN</CivilizationType>
		<BuildingClassType>BUILDINGCLASS_DREAM_TWISTER</BuildingClassType>
		<BuildingType/>
	</Row>
	<Row>
		<CivilizationType>CIVILIZATION_MINOR</CivilizationType>
		<BuildingClassType>BUILDINGCLASS_DREAM_TWISTER</BuildingClassType>
		<BuildingType/>
	</Row>
	<Row>
		<CivilizationType>CIVILIZATION_BARBARIAN</CivilizationType>
		<BuildingClassType>BUILDINGCLASS_EMPATH_GUILD</BuildingClassType>
		<BuildingType/>
	</Row>
	<Row>
		<CivilizationType>CIVILIZATION_MINOR</CivilizationType>
		<BuildingClassType>BUILDINGCLASS_EMPATH_GUILD</BuildingClassType>
		<BuildingType/>
	</Row>
	<Row>
		<CivilizationType>CIVILIZATION_BARBARIAN</CivilizationType>
		<BuildingClassType>BUILDINGCLASS_BULK_MATTER_TRANSMITTER</BuildingClassType>
		<BuildingType/>
	</Row>
	<Row>
		<CivilizationType>CIVILIZATION_MINOR</CivilizationType>
		<BuildingClassType>BUILDINGCLASS_BULK_MATTER_TRANSMITTER</BuildingClassType>
		<BuildingType/>
	</Row>
	<Row>
		<CivilizationType>CIVILIZATION_BARBARIAN</CivilizationType>
		<BuildingClassType>BUILDINGCLASS_FCITY</BuildingClassType>
		<BuildingType/>
	</Row>
	<Row>
		<CivilizationType>CIVILIZATION_MINOR</CivilizationType>
		<BuildingClassType>BUILDINGCLASS_FCITY</BuildingClassType>
		<BuildingType/>
	</Row>
	<Row>
		<CivilizationType>CIVILIZATION_BARBARIAN</CivilizationType>
		<BuildingClassType>BUILDINGCLASS_OCITY</BuildingClassType>
		<BuildingType/>
	</Row>
	<Row>
		<CivilizationType>CIVILIZATION_MINOR</CivilizationType>
		<BuildingClassType>BUILDINGCLASS_OCITY</BuildingClassType>
		<BuildingType/>
	</Row>
	<Row>
		<CivilizationType>CIVILIZATION_BARBARIAN</CivilizationType>
		<BuildingClassType>BUILDINGCLASS_WDOME</BuildingClassType>
		<BuildingType/>
	</Row>
	<Row>
		<CivilizationType>CIVILIZATION_MINOR</CivilizationType>
		<BuildingClassType>BUILDINGCLASS_WDOME</BuildingClassType>
		<BuildingType/>
	</Row>
	<Row>
		<CivilizationType>CIVILIZATION_BARBARIAN</CivilizationType>
		<BuildingClassType>BUILDINGCLASS_LUNI</BuildingClassType>
		<BuildingType/>
	</Row>
	<Row>
		<CivilizationType>CIVILIZATION_MINOR</CivilizationType>
		<BuildingClassType>BUILDINGCLASS_LUNI</BuildingClassType>
		<BuildingType/>
	</Row>
	<Row>
		<CivilizationType>CIVILIZATION_BARBARIAN</CivilizationType>
		<BuildingClassType>BUILDINGCLASS_BAYER</BuildingClassType>
		<BuildingType/>
	</Row>
	<Row>
		<CivilizationType>CIVILIZATION_MINOR</CivilizationType>
		<BuildingClassType>BUILDINGCLASS_BAYER</BuildingClassType>
		<BuildingType/>
	</Row>
	<Row>
		<CivilizationType>CIVILIZATION_BARBARIAN</CivilizationType>
		<BuildingClassType>BUILDINGCLASS_SOTOWER</BuildingClassType>
		<BuildingType/>
	</Row>
	<Row>
		<CivilizationType>CIVILIZATION_MINOR</CivilizationType>
		<BuildingClassType>BUILDINGCLASS_SOTOWER</BuildingClassType>
		<BuildingType/>
	</Row>
	<Row>
		<CivilizationType>CIVILIZATION_BARBARIAN</CivilizationType>
		<BuildingClassType>BUILDINGCLASS_AKRO</BuildingClassType>
		<BuildingType/>
	</Row>
	<Row>
		<CivilizationType>CIVILIZATION_MINOR</CivilizationType>
		<BuildingClassType>BUILDINGCLASS_AKRO</BuildingClassType>
		<BuildingType/>
	</Row>
	<Row>
		<CivilizationType>CIVILIZATION_BARBARIAN</CivilizationType>
		<BuildingClassType>BUILDINGCLASS_GUNUNG</BuildingClassType>
		<BuildingType/>
	</Row>
	<Row>
		<CivilizationType>CIVILIZATION_MINOR</CivilizationType>
		<BuildingClassType>BUILDINGCLASS_GUNUNG</BuildingClassType>
		<BuildingType/>
	</Row>
	<Row>
		<CivilizationType>CIVILIZATION_BARBARIAN</CivilizationType>
		<BuildingClassType>BUILDINGCLASS_UGARIT</BuildingClassType>
		<BuildingType/>
	</Row>
	<Row>
		<CivilizationType>CIVILIZATION_MINOR</CivilizationType>
		<BuildingClassType>BUILDINGCLASS_UGARIT</BuildingClassType>
		<BuildingType/>
	</Row>
	<Row>
		<CivilizationType>CIVILIZATION_BARBARIAN</CivilizationType>
		<BuildingClassType>BUILDINGCLASS_REGISTAN</BuildingClassType>
		<BuildingType/>
	</Row>
	<Row>
		<CivilizationType>CIVILIZATION_MINOR</CivilizationType>
		<BuildingClassType>BUILDINGCLASS_REGISTAN</BuildingClassType>
		<BuildingType/>
	</Row>
	<Row>
		<CivilizationType>CIVILIZATION_BARBARIAN</CivilizationType>
		<BuildingClassType>BUILDINGCLASS_MARIA</BuildingClassType>
		<BuildingType/>
	</Row>
	<Row>
		<CivilizationType>CIVILIZATION_MINOR</CivilizationType>
		<BuildingClassType>BUILDINGCLASS_MARIA</BuildingClassType>
		<BuildingType/>
	</Row>
	<Row>
		<CivilizationType>CIVILIZATION_BARBARIAN</CivilizationType>
		<BuildingClassType>BUILDINGCLASS_VENICE</BuildingClassType>
		<BuildingType/>
	</Row>
	<Row>
		<CivilizationType>CIVILIZATION_MINOR</CivilizationType>
		<BuildingClassType>BUILDINGCLASS_VENICE</BuildingClassType>
		<BuildingType/>
	</Row>
	<Row>
		<CivilizationType>CIVILIZATION_BARBARIAN</CivilizationType>
		<BuildingClassType>BUILDINGCLASS_PUUKOHOLA_HEIAU</BuildingClassType>
		<BuildingType/>
	</Row>
	<Row>
		<CivilizationType>CIVILIZATION_MINOR</CivilizationType>
		<BuildingClassType>BUILDINGCLASS_PUUKOHOLA_HEIAU</BuildingClassType>
		<BuildingType/>
	</Row>
	<Row>
		<CivilizationType>CIVILIZATION_BARBARIAN</CivilizationType>
		<BuildingClassType>BUILDINGCLASS_PETERHOF</BuildingClassType>
		<BuildingType/>
	</Row>
	<Row>
		<CivilizationType>CIVILIZATION_MINOR</CivilizationType>
		<BuildingClassType>BUILDINGCLASS_PETERHOF</BuildingClassType>
		<BuildingType/>
	</Row>
	<Row>
		<CivilizationType>CIVILIZATION_BARBARIAN</CivilizationType>
		<BuildingClassType>BUILDINGCLASS_SELIMIYE</BuildingClassType>
		<BuildingType/>
	</Row>
	<Row>
		<CivilizationType>CIVILIZATION_MINOR</CivilizationType>
		<BuildingClassType>BUILDINGCLASS_SELIMIYE</BuildingClassType>
		<BuildingType/>
	</Row>
	<Row>
		<CivilizationType>CIVILIZATION_BARBARIAN</CivilizationType>
		<BuildingClassType>BUILDINGCLASS_SHAHI</BuildingClassType>
		<BuildingType/>
	</Row>
	<Row>
		<CivilizationType>CIVILIZATION_MINOR</CivilizationType>
		<BuildingClassType>BUILDINGCLASS_SHAHI</BuildingClassType>
		<BuildingType/>
	</Row>
	<Row>
		<CivilizationType>CIVILIZATION_BARBARIAN</CivilizationType>
		<BuildingClassType>BUILDINGCLASS_UMAYYAD</BuildingClassType>
		<BuildingType/>
	</Row>
	<Row>
		<CivilizationType>CIVILIZATION_MINOR</CivilizationType>
		<BuildingClassType>BUILDINGCLASS_UMAYYAD</BuildingClassType>
		<BuildingType/>
	</Row>
	<Row>
		<CivilizationType>CIVILIZATION_BARBARIAN</CivilizationType>
		<BuildingClassType>BUILDINGCLASS_MEVLANA</BuildingClassType>
		<BuildingType/>
	</Row>
	<Row>
		<CivilizationType>CIVILIZATION_MINOR</CivilizationType>
		<BuildingClassType>BUILDINGCLASS_MEVLANA</BuildingClassType>
		<BuildingType/>
	</Row>
	<Row>
		<CivilizationType>CIVILIZATION_BARBARIAN</CivilizationType>
		<BuildingClassType>BUILDINGCLASS_HUNGARYPARLIAMENT</BuildingClassType>
		<BuildingType/>
	</Row>
	<Row>
		<CivilizationType>CIVILIZATION_MINOR</CivilizationType>
		<BuildingClassType>BUILDINGCLASS_HUNGARYPARLIAMENT</BuildingClassType>
		<BuildingType/>
	</Row>
	<Row>
		<CivilizationType>CIVILIZATION_BARBARIAN</CivilizationType>
		<BuildingClassType>BUILDINGCLASS_TRAFALGAR</BuildingClassType>
		<BuildingType/>
	</Row>
	<Row>
		<CivilizationType>CIVILIZATION_MINOR</CivilizationType>
		<BuildingClassType>BUILDINGCLASS_TRAFALGAR</BuildingClassType>
		<BuildingType/>
	</Row>
	<Row>
		<CivilizationType>CIVILIZATION_BARBARIAN</CivilizationType>
		<BuildingClassType>BUILDINGCLASS_NQJ</BuildingClassType>
		<BuildingType/>
	</Row>
	<Row>
		<CivilizationType>CIVILIZATION_MINOR</CivilizationType>
		<BuildingClassType>BUILDINGCLASS_NQJ</BuildingClassType>
		<BuildingType/>
	</Row>
	<Row>
		<CivilizationType>CIVILIZATION_BARBARIAN</CivilizationType>
		<BuildingClassType>BUILDINGCLASS_BAGAN</BuildingClassType>
		<BuildingType/>
	</Row>
	<Row>
		<CivilizationType>CIVILIZATION_MINOR</CivilizationType>
		<BuildingClassType>BUILDINGCLASS_BAGAN</BuildingClassType>
		<BuildingType/>
	</Row>
	<Row>
		<CivilizationType>CIVILIZATION_BARBARIAN</CivilizationType>
		<BuildingClassType>BUILDINGCLASS_PRAGUE_CASTLE</BuildingClassType>
		<BuildingType/>
	</Row>
	<Row>
		<CivilizationType>CIVILIZATION_MINOR</CivilizationType>
		<BuildingClassType>BUILDINGCLASS_PRAGUE_CASTLE</BuildingClassType>
		<BuildingType/>
	</Row>
	<Row>
		<CivilizationType>CIVILIZATION_BARBARIAN</CivilizationType>
		<BuildingClassType>BUILDINGCLASS_MUSEUM_ISLAND</BuildingClassType>
		<BuildingType/>
	</Row>
	<Row>
		<CivilizationType>CIVILIZATION_MINOR</CivilizationType>
		<BuildingClassType>BUILDINGCLASS_MUSEUM_ISLAND</BuildingClassType>
		<BuildingType/>
	</Row>
	<Row>
		<CivilizationType>CIVILIZATION_BARBARIAN</CivilizationType>
		<BuildingClassType>BUILDINGCLASS_FREEDOMTOWER</BuildingClassType>
		<BuildingType/>
	</Row>
	<Row>
		<CivilizationType>CIVILIZATION_MINOR</CivilizationType>
		<BuildingClassType>BUILDINGCLASS_FREEDOMTOWER</BuildingClassType>
		<BuildingType/>
	</Row>
	<Row>
		<CivilizationType>CIVILIZATION_BARBARIAN</CivilizationType>
		<BuildingClassType>BUILDINGCLASS_WESTMINSTER</BuildingClassType>
		<BuildingType/>
	</Row>
	<Row>
		<CivilizationType>CIVILIZATION_MINOR</CivilizationType>
		<BuildingClassType>BUILDINGCLASS_WESTMINSTER</BuildingClassType>
		<BuildingType/>
	</Row>
	<Row>
		<CivilizationType>CIVILIZATION_BARBARIAN</CivilizationType>
		<BuildingClassType>BUILDINGCLASS_TRIOMPHE</BuildingClassType>
		<BuildingType/>
	</Row>
	<Row>
		<CivilizationType>CIVILIZATION_MINOR</CivilizationType>
		<BuildingClassType>BUILDINGCLASS_TRIOMPHE</BuildingClassType>
		<BuildingType/>
	</Row>
	<Row>
		<CivilizationType>CIVILIZATION_BARBARIAN</CivilizationType>
		<BuildingClassType>BUILDINGCLASS_MONTE_CARLO</BuildingClassType>
		<BuildingType/>
	</Row>
	<Row>
		<CivilizationType>CIVILIZATION_MINOR</CivilizationType>
		<BuildingClassType>BUILDINGCLASS_MONTE_CARLO</BuildingClassType>
		<BuildingType/>
	</Row>
	<Row>
		<CivilizationType>CIVILIZATION_BARBARIAN</CivilizationType>
		<BuildingClassType>BUILDINGCLASS_KIYOMIZU</BuildingClassType>
		<BuildingType/>
	</Row>
	<Row>
		<CivilizationType>CIVILIZATION_MINOR</CivilizationType>
		<BuildingClassType>BUILDINGCLASS_KIYOMIZU</BuildingClassType>
		<BuildingType/>
	</Row>
	<Row>
		<CivilizationType>CIVILIZATION_BARBARIAN</CivilizationType>
		<BuildingClassType>BUILDINGCLASS_PAUL</BuildingClassType>
		<BuildingType/>
	</Row>
	<Row>
		<CivilizationType>CIVILIZATION_MINOR</CivilizationType>
		<BuildingClassType>BUILDINGCLASS_PAUL</BuildingClassType>
		<BuildingType/>
	</Row>
	<Row>
		<CivilizationType>CIVILIZATION_BARBARIAN</CivilizationType>
		<BuildingClassType>BUILDINGCLASS_GRAND_PALACE</BuildingClassType>
		<BuildingType/>
	</Row>
	<Row>
		<CivilizationType>CIVILIZATION_MINOR</CivilizationType>
		<BuildingClassType>BUILDINGCLASS_GRAND_PALACE</BuildingClassType>
		<BuildingType/>
	</Row>
	<Row>
		<CivilizationType>CIVILIZATION_BARBARIAN</CivilizationType>
		<BuildingClassType>BUILDINGCLASS_TAISHAN</BuildingClassType>
		<BuildingType/>
	</Row>
	<Row>
		<CivilizationType>CIVILIZATION_MINOR</CivilizationType>
		<BuildingClassType>BUILDINGCLASS_TAISHAN</BuildingClassType>
		<BuildingType/>
	</Row>
	<Row>
		<CivilizationType>CIVILIZATION_BARBARIAN</CivilizationType>
		<BuildingClassType>BUILDINGCLASS_PERSEPOLIS</BuildingClassType>
		<BuildingType/>
	</Row>
	<Row>
		<CivilizationType>CIVILIZATION_MINOR</CivilizationType>
		<BuildingClassType>BUILDINGCLASS_PERSEPOLIS</BuildingClassType>
		<BuildingType/>
	</Row>
	<Row>
		<CivilizationType>CIVILIZATION_BARBARIAN</CivilizationType>
		<BuildingClassType>BUILDINGCLASS_HMEXICO</BuildingClassType>
		<BuildingType/>
	</Row>
	<Row>
		<CivilizationType>CIVILIZATION_MINOR</CivilizationType>
		<BuildingClassType>BUILDINGCLASS_HMEXICO</BuildingClassType>
		<BuildingType/>
	</Row>
	<Row>
		<CivilizationType>CIVILIZATION_BARBARIAN</CivilizationType>
		<BuildingClassType>BUILDINGCLASS_MADAIN_SALEH</BuildingClassType>
		<BuildingType/>
	</Row>
	<Row>
		<CivilizationType>CIVILIZATION_MINOR</CivilizationType>
		<BuildingClassType>BUILDINGCLASS_MADAIN_SALEH</BuildingClassType>
		<BuildingType/>
	</Row>
	<Row>
		<CivilizationType>CIVILIZATION_BARBARIAN</CivilizationType>
		<BuildingClassType>BUILDINGCLASS_ROM</BuildingClassType>
		<BuildingType/>
	</Row>
	<Row>
		<CivilizationType>CIVILIZATION_MINOR</CivilizationType>
		<BuildingClassType>BUILDINGCLASS_ROM</BuildingClassType>
		<BuildingType/>
	</Row>
	<Row>
		<CivilizationType>CIVILIZATION_BARBARIAN</CivilizationType>
		<BuildingClassType>BUILDINGCLASS_FIRSTBANK</BuildingClassType>
		<BuildingType/>
	</Row>
	<Row>
		<CivilizationType>CIVILIZATION_MINOR</CivilizationType>
		<BuildingClassType>BUILDINGCLASS_FIRSTBANK</BuildingClassType>
		<BuildingType/>
	</Row>
	<Row>
		<CivilizationType>CIVILIZATION_BARBARIAN</CivilizationType>
		<BuildingClassType>BUILDINGCLASS_MIAPOLISCT</BuildingClassType>
		<BuildingType/>
	</Row>
	<Row>
		<CivilizationType>CIVILIZATION_MINOR</CivilizationType>
		<BuildingClassType>BUILDINGCLASS_MIAPOLISCT</BuildingClassType>
		<BuildingType/>
	</Row>
	<Row>
		<CivilizationType>CIVILIZATION_BARBARIAN</CivilizationType>
		<BuildingClassType>BUILDINGCLASS_NOTREDAME_MONTREAL</BuildingClassType>
		<BuildingType/>
	</Row>
	<Row>
		<CivilizationType>CIVILIZATION_MINOR</CivilizationType>
		<BuildingClassType>BUILDINGCLASS_NOTREDAME_MONTREAL</BuildingClassType>
		<BuildingType/>
	</Row>
	<Row>
		<CivilizationType>CIVILIZATION_BARBARIAN</CivilizationType>
		<BuildingClassType>BUILDINGCLASS_MEDINAMARRAKECH</BuildingClassType>
		<BuildingType/>
	</Row>
	<Row>
		<CivilizationType>CIVILIZATION_MINOR</CivilizationType>
		<BuildingClassType>BUILDINGCLASS_MEDINAMARRAKECH</BuildingClassType>
		<BuildingType/>
	</Row>
	<Row>
		<CivilizationType>CIVILIZATION_BARBARIAN</CivilizationType>
		<BuildingClassType>BUILDINGCLASS_UCH</BuildingClassType>
		<BuildingType/>
	</Row>
	<Row>
		<CivilizationType>CIVILIZATION_MINOR</CivilizationType>
		<BuildingClassType>BUILDINGCLASS_UCH</BuildingClassType>
		<BuildingType/>
	</Row>
	<Row>
		<CivilizationType>CIVILIZATION_BARBARIAN</CivilizationType>
		<BuildingClassType>BUILDINGCLASS_PREAL</BuildingClassType>
		<BuildingType/>
	</Row>
	<Row>
		<CivilizationType>CIVILIZATION_MINOR</CivilizationType>
		<BuildingClassType>BUILDINGCLASS_PREAL</BuildingClassType>
		<BuildingType/>
	</Row>
	<Row>
		<CivilizationType>CIVILIZATION_BARBARIAN</CivilizationType>
		<BuildingClassType>BUILDINGCLASS_RIJKSMUSEUM</BuildingClassType>
		<BuildingType/>
	</Row>
	<Row>
		<CivilizationType>CIVILIZATION_MINOR</CivilizationType>
		<BuildingClassType>BUILDINGCLASS_RIJKSMUSEUM</BuildingClassType>
		<BuildingType/>
	</Row>
	<Row>
		<CivilizationType>CIVILIZATION_BARBARIAN</CivilizationType>
		<BuildingClassType>BUILDINGCLASS_FUJIAN</BuildingClassType>
		<BuildingType/>
	</Row>
	<Row>
		<CivilizationType>CIVILIZATION_MINOR</CivilizationType>
		<BuildingClassType>BUILDINGCLASS_FUJIAN</BuildingClassType>
		<BuildingType/>
	</Row>
	<Row>
		<CivilizationType>CIVILIZATION_BARBARIAN</CivilizationType>
		<BuildingClassType>BUILDINGCLASS_THEATRO_MUNICIPAL</BuildingClassType>
		<BuildingType/>
	</Row>
	<Row>
		<CivilizationType>CIVILIZATION_MINOR</CivilizationType>
		<BuildingClassType>BUILDINGCLASS_THEATRO_MUNICIPAL</BuildingClassType>
		<BuildingType/>
	</Row>
	<Row>
		<CivilizationType>CIVILIZATION_BARBARIAN</CivilizationType>
		<BuildingClassType>BUILDINGCLASS_ANDREWKIEV</BuildingClassType>
		<BuildingType/>
	</Row>
	<Row>
		<CivilizationType>CIVILIZATION_MINOR</CivilizationType>
		<BuildingClassType>BUILDINGCLASS_ANDREWKIEV</BuildingClassType>
		<BuildingType/>
	</Row>
	<Row>
		<CivilizationType>CIVILIZATION_BARBARIAN</CivilizationType>
		<BuildingClassType>BUILDINGCLASS_CHEVALIERS</BuildingClassType>
		<BuildingType/>
	</Row>
	<Row>
		<CivilizationType>CIVILIZATION_MINOR</CivilizationType>
		<BuildingClassType>BUILDINGCLASS_CHEVALIERS</BuildingClassType>
		<BuildingType/>
	</Row>
	<Row>
		<CivilizationType>CIVILIZATION_BARBARIAN</CivilizationType>
		<BuildingClassType>BUILDINGCLASS_GYEONGBOKGUNG</BuildingClassType>
		<BuildingType/>
	</Row>
	<Row>
		<CivilizationType>CIVILIZATION_MINOR</CivilizationType>
		<BuildingClassType>BUILDINGCLASS_GYEONGBOKGUNG</BuildingClassType>
		<BuildingType/>
	</Row>
	<Row>
		<CivilizationType>CIVILIZATION_BARBARIAN</CivilizationType>
		<BuildingClassType>BUILDINGCLASS_KAIROUAN</BuildingClassType>
		<BuildingType/>
	</Row>
	<Row>
		<CivilizationType>CIVILIZATION_MINOR</CivilizationType>
		<BuildingClassType>BUILDINGCLASS_KAIROUAN</BuildingClassType>
		<BuildingType/>
	</Row>
	<Row>
		<CivilizationType>CIVILIZATION_BARBARIAN</CivilizationType>
		<BuildingClassType>BUILDINGCLASS_MET</BuildingClassType>
		<BuildingType/>
	</Row>
	<Row>
		<CivilizationType>CIVILIZATION_MINOR</CivilizationType>
		<BuildingClassType>BUILDINGCLASS_MET</BuildingClassType>
		<BuildingType/>
	</Row>
	<Row>
		<CivilizationType>CIVILIZATION_BARBARIAN</CivilizationType>
		<BuildingClassType>BUILDINGCLASS_WILLIS</BuildingClassType>
		<BuildingType/>
	</Row>
	<Row>
		<CivilizationType>CIVILIZATION_MINOR</CivilizationType>
		<BuildingClassType>BUILDINGCLASS_WILLIS</BuildingClassType>
		<BuildingType/>
	</Row>
	<Row>
		<CivilizationType>CIVILIZATION_BARBARIAN</CivilizationType>
		<BuildingClassType>BUILDINGCLASS_HOHENZOLLERN</BuildingClassType>
		<BuildingType/>
	</Row>
	<Row>
		<CivilizationType>CIVILIZATION_MINOR</CivilizationType>
		<BuildingClassType>BUILDINGCLASS_HOHENZOLLERN</BuildingClassType>
		<BuildingType/>
	</Row>
	<Row>
		<CivilizationType>CIVILIZATION_BARBARIAN</CivilizationType>
		<BuildingClassType>BUILDINGCLASS_BARDO</BuildingClassType>
		<BuildingType/>
	</Row>
	<Row>
		<CivilizationType>CIVILIZATION_MINOR</CivilizationType>
		<BuildingClassType>BUILDINGCLASS_BARDO</BuildingClassType>
		<BuildingType/>
	</Row>
	<Row>
		<CivilizationType>CIVILIZATION_BARBARIAN</CivilizationType>
		<BuildingClassType>BUILDINGCLASS_VERSAILLES</BuildingClassType>
		<BuildingType/>
	</Row>
	<Row>
		<CivilizationType>CIVILIZATION_MINOR</CivilizationType>
		<BuildingClassType>BUILDINGCLASS_VERSAILLES</BuildingClassType>
		<BuildingType/>
	</Row>
	<Row>
		<CivilizationType>CIVILIZATION_BARBARIAN</CivilizationType>
		<BuildingClassType>BUILDINGCLASS_SCHONBRUNN</BuildingClassType>
		<BuildingType/>
	</Row>
	<Row>
		<CivilizationType>CIVILIZATION_MINOR</CivilizationType>
		<BuildingClassType>BUILDINGCLASS_SCHONBRUNN</BuildingClassType>
		<BuildingType/>
	</Row>
	<Row>
		<CivilizationType>CIVILIZATION_BARBARIAN</CivilizationType>
		<BuildingClassType>BUILDINGCLASS_GRANDDHABI</BuildingClassType>
		<BuildingType/>
	</Row>
	<Row>
		<CivilizationType>CIVILIZATION_MINOR</CivilizationType>
		<BuildingClassType>BUILDINGCLASS_GRANDDHABI</BuildingClassType>
		<BuildingType/>
	</Row>
	<Row>
		<CivilizationType>CIVILIZATION_BARBARIAN</CivilizationType>
		<BuildingClassType>BUILDINGCLASS_ARUN</BuildingClassType>
		<BuildingType/>
	</Row>
	<Row>
		<CivilizationType>CIVILIZATION_MINOR</CivilizationType>
		<BuildingClassType>BUILDINGCLASS_ARUN</BuildingClassType>
		<BuildingType/>
	</Row>
	<Row>
		<CivilizationType>CIVILIZATION_BARBARIAN</CivilizationType>
		<BuildingClassType>BUILDINGCLASS_KANDY_TEMPLE</BuildingClassType>
		<BuildingType/>
	</Row>
	<Row>
		<CivilizationType>CIVILIZATION_MINOR</CivilizationType>
		<BuildingClassType>BUILDINGCLASS_KANDY_TEMPLE</BuildingClassType>
		<BuildingType/>
	</Row>
	<Row>
		<CivilizationType>CIVILIZATION_BARBARIAN</CivilizationType>
		<BuildingClassType>BUILDINGCLASS_YAZD</BuildingClassType>
		<BuildingType/>
	</Row>
	<Row>
		<CivilizationType>CIVILIZATION_MINOR</CivilizationType>
		<BuildingClassType>BUILDINGCLASS_YAZD</BuildingClassType>
		<BuildingType/>
	</Row>
	<Row>
		<CivilizationType>CIVILIZATION_BARBARIAN</CivilizationType>
		<BuildingClassType>BUILDINGCLASS_SANTIAGO</BuildingClassType>
		<BuildingType/>
	</Row>
	<Row>
		<CivilizationType>CIVILIZATION_MINOR</CivilizationType>
		<BuildingClassType>BUILDINGCLASS_SANTIAGO</BuildingClassType>
		<BuildingType/>
	</Row>
	<Row>
		<CivilizationType>CIVILIZATION_BARBARIAN</CivilizationType>
		<BuildingClassType>BUILDINGCLASS_DOLMABAHCE</BuildingClassType>
		<BuildingType/>
	</Row>
	<Row>
		<CivilizationType>CIVILIZATION_MINOR</CivilizationType>
		<BuildingClassType>BUILDINGCLASS_DOLMABAHCE</BuildingClassType>
		<BuildingType/>
	</Row>
	<Row>
		<CivilizationType>CIVILIZATION_BARBARIAN</CivilizationType>
		<BuildingClassType>BUILDINGCLASS_CARTAGENA</BuildingClassType>
		<BuildingType/>
	</Row>
	<Row>
		<CivilizationType>CIVILIZATION_MINOR</CivilizationType>
		<BuildingClassType>BUILDINGCLASS_CARTAGENA</BuildingClassType>
		<BuildingType/>
	</Row>
	<Row>
		<CivilizationType>CIVILIZATION_BARBARIAN</CivilizationType>
		<BuildingClassType>BUILDINGCLASS_ALAQSA</BuildingClassType>
		<BuildingType/>
	</Row>
	<Row>
		<CivilizationType>CIVILIZATION_MINOR</CivilizationType>
		<BuildingClassType>BUILDINGCLASS_ALAQSA</BuildingClassType>
		<BuildingType/>
	</Row>
	<Row>
		<CivilizationType>CIVILIZATION_BARBARIAN</CivilizationType>
		<BuildingClassType>BUILDINGCLASS_ROYAL_CASTLE</BuildingClassType>
		<BuildingType/>
	</Row>
	<Row>
		<CivilizationType>CIVILIZATION_MINOR</CivilizationType>
		<BuildingClassType>BUILDINGCLASS_ROYAL_CASTLE</BuildingClassType>
		<BuildingType/>
	</Row>
	<Row>
		<CivilizationType>CIVILIZATION_BARBARIAN</CivilizationType>
		<BuildingClassType>BUILDINGCLASS_COLON</BuildingClassType>
		<BuildingType/>
	</Row>
	<Row>
		<CivilizationType>CIVILIZATION_MINOR</CivilizationType>
		<BuildingClassType>BUILDINGCLASS_COLON</BuildingClassType>
		<BuildingType/>
	</Row>
	<Row>
		<CivilizationType>CIVILIZATION_BARBARIAN</CivilizationType>
		<BuildingClassType>BUILDINGCLASS_OTTAWAGOVERN</BuildingClassType>
		<BuildingType/>
	</Row>
	<Row>
		<CivilizationType>CIVILIZATION_MINOR</CivilizationType>
		<BuildingClassType>BUILDINGCLASS_OTTAWAGOVERN</BuildingClassType>
		<BuildingType/>
	</Row>
	<Row>
		<CivilizationType>CIVILIZATION_BARBARIAN</CivilizationType>
		<BuildingClassType>BUILDINGCLASS_MBAYSANDS</BuildingClassType>
		<BuildingType/>
	</Row>
	<Row>
		<CivilizationType>CIVILIZATION_MINOR</CivilizationType>
		<BuildingClassType>BUILDINGCLASS_MBAYSANDS</BuildingClassType>
		<BuildingType/>
	</Row>
	<Row>
		<CivilizationType>CIVILIZATION_BARBARIAN</CivilizationType>
		<BuildingClassType>BUILDINGCLASS_KEUKONHOF</BuildingClassType>
		<BuildingType/>
	</Row>
	<Row>
		<CivilizationType>CIVILIZATION_MINOR</CivilizationType>
		<BuildingClassType>BUILDINGCLASS_KEUKONHOF</BuildingClassType>
		<BuildingType/>
	</Row>
	<Row>
		<CivilizationType>CIVILIZATION_BARBARIAN</CivilizationType>
		<BuildingClassType>BUILDINGCLASS_GRANDBAZAAR</BuildingClassType>
		<BuildingType/>
	</Row>
	<Row>
		<CivilizationType>CIVILIZATION_MINOR</CivilizationType>
		<BuildingClassType>BUILDINGCLASS_GRANDBAZAAR</BuildingClassType>
		<BuildingType/>
	</Row>
	<Row>
		<CivilizationType>CIVILIZATION_BARBARIAN</CivilizationType>
		<BuildingClassType>BUILDINGCLASS_BELLAGIO</BuildingClassType>
		<BuildingType/>
	</Row>
	<Row>
		<CivilizationType>CIVILIZATION_MINOR</CivilizationType>
		<BuildingClassType>BUILDINGCLASS_BELLAGIO</BuildingClassType>
		<BuildingType/>
	</Row>
	<Row>
		<CivilizationType>CIVILIZATION_BARBARIAN</CivilizationType>
		<BuildingClassType>BUILDINGCLASS_GARNIER</BuildingClassType>
		<BuildingType/>
	</Row>
	<Row>
		<CivilizationType>CIVILIZATION_MINOR</CivilizationType>
		<BuildingClassType>BUILDINGCLASS_GARNIER</BuildingClassType>
		<BuildingType/>
	</Row>
	<Row>
		<CivilizationType>CIVILIZATION_BARBARIAN</CivilizationType>
		<BuildingClassType>BUILDINGCLASS_RILA</BuildingClassType>
		<BuildingType/>
	</Row>
	<Row>
		<CivilizationType>CIVILIZATION_MINOR</CivilizationType>
		<BuildingClassType>BUILDINGCLASS_RILA</BuildingClassType>
		<BuildingType/>
	</Row>
	<Row>
		<CivilizationType>CIVILIZATION_BARBARIAN</CivilizationType>
		<BuildingClassType>BUILDINGCLASS_LA_MAESTRANZA</BuildingClassType>
		<BuildingType/>
	</Row>
	<Row>
		<CivilizationType>CIVILIZATION_MINOR</CivilizationType>
		<BuildingClassType>BUILDINGCLASS_LA_MAESTRANZA</BuildingClassType>
		<BuildingType/>
	</Row>
	<Row>
		<CivilizationType>CIVILIZATION_BARBARIAN</CivilizationType>
		<BuildingClassType>BUILDINGCLASS_ASSISI</BuildingClassType>
		<BuildingType/>
	</Row>
	<Row>
		<CivilizationType>CIVILIZATION_MINOR</CivilizationType>
		<BuildingClassType>BUILDINGCLASS_PAUL</BuildingClassType>
		<BuildingType/>
	</Row>
	<Row>
		<CivilizationType>CIVILIZATION_BARBARIAN</CivilizationType>
		<BuildingClassType>BUILDINGCLASS_NABWI</BuildingClassType>
		<BuildingType/>
	</Row>
	<Row>
		<CivilizationType>CIVILIZATION_MINOR</CivilizationType>
		<BuildingClassType>BUILDINGCLASS_NABWI</BuildingClassType>
		<BuildingType/>
	</Row>
	<Row>
		<CivilizationType>CIVILIZATION_BARBARIAN</CivilizationType>
		<BuildingClassType>BUILDINGCLASS_STAMBHA</BuildingClassType>
		<BuildingType/>
	</Row>
	<Row>
		<CivilizationType>CIVILIZATION_MINOR</CivilizationType>
		<BuildingClassType>BUILDINGCLASS_STAMBHA</BuildingClassType>
		<BuildingType/>
	</Row>
	<Row>
		<CivilizationType>CIVILIZATION_BARBARIAN</CivilizationType>
		<BuildingClassType>BUILDINGCLASS_SUMMERP</BuildingClassType>
		<BuildingType/>
	</Row>
	<Row>
		<CivilizationType>CIVILIZATION_MINOR</CivilizationType>
		<BuildingClassType>BUILDINGCLASS_SUMMERP</BuildingClassType>
		<BuildingType/>
	</Row>
	<Row>
		<CivilizationType>CIVILIZATION_BARBARIAN</CivilizationType>
		<BuildingClassType>BUILDINGCLASS_PRACA_COMERCIO</BuildingClassType>
		<BuildingType/>
	</Row>
	<Row>
		<CivilizationType>CIVILIZATION_MINOR</CivilizationType>
		<BuildingClassType>BUILDINGCLASS_PRACA_COMERCIO</BuildingClassType>
		<BuildingType/>
	</Row>
	<Row>
		<CivilizationType>CIVILIZATION_BARBARIAN</CivilizationType>
		<BuildingClassType>BUILDINGCLASS_PAMUKKALE</BuildingClassType>
		<BuildingType/>
	</Row>
	<Row>
		<CivilizationType>CIVILIZATION_MINOR</CivilizationType>
		<BuildingClassType>BUILDINGCLASS_PAMUKKALE</BuildingClassType>
		<BuildingType/>
	</Row>
	<Row>
		<CivilizationType>CIVILIZATION_BARBARIAN</CivilizationType>
		<BuildingClassType>BUILDINGCLASS_MATSUMOTO</BuildingClassType>
		<BuildingType/>
	</Row>
	<Row>
		<CivilizationType>CIVILIZATION_MINOR</CivilizationType>
		<BuildingClassType>BUILDINGCLASS_MATSUMOTO</BuildingClassType>
		<BuildingType/>
	</Row>
	<Row>
		<CivilizationType>CIVILIZATION_BARBARIAN</CivilizationType>
		<BuildingClassType>BUILDINGCLASS_HOFBURG</BuildingClassType>
		<BuildingType/>
	</Row>
	<Row>
		<CivilizationType>CIVILIZATION_MINOR</CivilizationType>
		<BuildingClassType>BUILDINGCLASS_HOFBURG</BuildingClassType>
		<BuildingType/>
	</Row>
	<Row>
		<CivilizationType>CIVILIZATION_BARBARIAN</CivilizationType>
		<BuildingClassType>BUILDINGCLASS_BETHCHURCH</BuildingClassType>
		<BuildingType/>
	</Row>
	<Row>
		<CivilizationType>CIVILIZATION_MINOR</CivilizationType>
		<BuildingClassType>BUILDINGCLASS_BETHCHURCH</BuildingClassType>
		<BuildingType/>
	</Row>
	<Row>
		<CivilizationType>CIVILIZATION_BARBARIAN</CivilizationType>
		<BuildingClassType>BUILDINGCLASS_CONSTANT_HIPPO</BuildingClassType>
		<BuildingType/>
	</Row>
	<Row>
		<CivilizationType>CIVILIZATION_MINOR</CivilizationType>
		<BuildingClassType>BUILDINGCLASS_CONSTANT_HIPPO</BuildingClassType>
		<BuildingType/>
	</Row>
	<Row>
		<CivilizationType>CIVILIZATION_BARBARIAN</CivilizationType>
		<BuildingClassType>BUILDINGCLASS_FORUM</BuildingClassType>
		<BuildingType/>
	</Row>
	<Row>
		<CivilizationType>CIVILIZATION_MINOR</CivilizationType>
		<BuildingClassType>BUILDINGCLASS_FORUM</BuildingClassType>
		<BuildingType/>
	</Row>
	<Row>
		<CivilizationType>CIVILIZATION_BARBARIAN</CivilizationType>
		<BuildingClassType>BUILDINGCLASS_ETEMENANKI</BuildingClassType>
		<BuildingType/>
	</Row>
	<Row>
		<CivilizationType>CIVILIZATION_MINOR</CivilizationType>
		<BuildingClassType>BUILDINGCLASS_ETEMENANKI</BuildingClassType>
		<BuildingType/>
	</Row>
	<Row>
		<CivilizationType>CIVILIZATION_BARBARIAN</CivilizationType>
		<BuildingClassType>BUILDINGCLASS_GARDENSUZHOU</BuildingClassType>
		<BuildingType/>
	</Row>
	<Row>
		<CivilizationType>CIVILIZATION_MINOR</CivilizationType>
		<BuildingClassType>BUILDINGCLASS_GARDENSUZHOU</BuildingClassType>
		<BuildingType/>
	</Row>
	<Row>
		<CivilizationType>CIVILIZATION_BARBARIAN</CivilizationType>
		<BuildingClassType>BUILDINGCLASS_ABER</BuildingClassType>
		<BuildingType/>
	</Row>
	<Row>
		<CivilizationType>CIVILIZATION_MINOR</CivilizationType>
		<BuildingClassType>BUILDINGCLASS_ABER</BuildingClassType>
		<BuildingType/>
	</Row>
	<Row>
		<CivilizationType>CIVILIZATION_BARBARIAN</CivilizationType>
		<BuildingClassType>BUILDINGCLASS_AGRA</BuildingClassType>
		<BuildingType/>
	</Row>
	<Row>
		<CivilizationType>CIVILIZATION_MINOR</CivilizationType>
		<BuildingClassType>BUILDINGCLASS_AGRA</BuildingClassType>
		<BuildingType/>
	</Row>
	<Row>
		<CivilizationType>CIVILIZATION_BARBARIAN</CivilizationType>
		<BuildingClassType>BUILDINGCLASS_HARMANDIR</BuildingClassType>
		<BuildingType/>
	</Row>
	<Row>
		<CivilizationType>CIVILIZATION_MINOR</CivilizationType>
		<BuildingClassType>BUILDINGCLASS_HARMANDIR</BuildingClassType>
		<BuildingType/>
	</Row>
	<Row>
		<CivilizationType>CIVILIZATION_BARBARIAN</CivilizationType>
		<BuildingClassType>BUILDINGCLASS_MAHADEVA</BuildingClassType>
		<BuildingType/>
	</Row>
	<Row>
		<CivilizationType>CIVILIZATION_MINOR</CivilizationType>
		<BuildingClassType>BUILDINGCLASS_MAHADEVA</BuildingClassType>
		<BuildingType/>
	</Row>
	<Row>
		<CivilizationType>CIVILIZATION_BARBARIAN</CivilizationType>
		<BuildingClassType>BUILDINGCLASS_HAWA</BuildingClassType>
		<BuildingType/>
	</Row>
	<Row>
		<CivilizationType>CIVILIZATION_MINOR</CivilizationType>
		<BuildingClassType>BUILDINGCLASS_HAWA</BuildingClassType>
		<BuildingType/>
	</Row>
	<Row>
		<CivilizationType>CIVILIZATION_BARBARIAN</CivilizationType>
		<BuildingClassType>BUILDINGCLASS_ALCATRAZ</BuildingClassType>
		<BuildingType/>
	</Row>
	<Row>
		<CivilizationType>CIVILIZATION_MINOR</CivilizationType>
		<BuildingClassType>BUILDINGCLASS_ALCATRAZ</BuildingClassType>
		<BuildingType/>
	</Row>
	<Row>
		<CivilizationType>CIVILIZATION_BARBARIAN</CivilizationType>
		<BuildingClassType>BUILDINGCLASS_EUREKA</BuildingClassType>
		<BuildingType/>
	</Row>
	<Row>
		<CivilizationType>CIVILIZATION_MINOR</CivilizationType>
		<BuildingClassType>BUILDINGCLASS_EUREKA</BuildingClassType>
		<BuildingType/>
	</Row>
	<Row>
		<CivilizationType>CIVILIZATION_BARBARIAN</CivilizationType>
		<BuildingClassType>BUILDINGCLASS_NIMROD</BuildingClassType>
		<BuildingType/>
	</Row>
	<Row>
		<CivilizationType>CIVILIZATION_MINOR</CivilizationType>
		<BuildingClassType>BUILDINGCLASS_NIMROD</BuildingClassType>
		<BuildingType/>
	</Row>
	<Row>
		<CivilizationType>CIVILIZATION_BARBARIAN</CivilizationType>
		<BuildingClassType>BUILDINGCLASS_FOUNDER_TEMPLE</BuildingClassType>
		<BuildingType/>
	</Row>
	<Row>
		<CivilizationType>CIVILIZATION_MINOR</CivilizationType>
		<BuildingClassType>BUILDINGCLASS_FOUNDER_TEMPLE</BuildingClassType>
		<BuildingType/>
	</Row>
	<Row>
		<CivilizationType>CIVILIZATION_BARBARIAN</CivilizationType>
		<BuildingClassType>BUILDINGCLASS_CARCASSONNE</BuildingClassType>
		<BuildingType/>
	</Row>
	<Row>
		<CivilizationType>CIVILIZATION_MINOR</CivilizationType>
		<BuildingClassType>BUILDINGCLASS_CARCASSONNE</BuildingClassType>
		<BuildingType/>
	</Row>
	<Row>
		<CivilizationType>CIVILIZATION_BARBARIAN</CivilizationType>
		<BuildingClassType>BUILDINGCLASS_ZANBIL</BuildingClassType>
		<BuildingType/>
	</Row>
	<Row>
		<CivilizationType>CIVILIZATION_MINOR</CivilizationType>
		<BuildingClassType>BUILDINGCLASS_ZANBIL</BuildingClassType>
		<BuildingType/>
	</Row>
	<Row>
		<CivilizationType>CIVILIZATION_BARBARIAN</CivilizationType>
		<BuildingClassType>BUILDINGCLASS_KRONBORG</BuildingClassType>
		<BuildingType/>
	</Row>
	<Row>
		<CivilizationType>CIVILIZATION_MINOR</CivilizationType>
		<BuildingClassType>BUILDINGCLASS_KRONBORG</BuildingClassType>
		<BuildingType/>
	</Row>
	<Row>
		<CivilizationType>CIVILIZATION_BARBARIAN</CivilizationType>
		<BuildingClassType>BUILDINGCLASS_MALBORK</BuildingClassType>
		<BuildingType/>
	</Row>
	<Row>
		<CivilizationType>CIVILIZATION_MINOR</CivilizationType>
		<BuildingClassType>BUILDINGCLASS_MALBORK</BuildingClassType>
		<BuildingType/>
	</Row>
	<Row>
		<CivilizationType>CIVILIZATION_BARBARIAN</CivilizationType>
		<BuildingClassType>BUILDINGCLASS_MONTMICHEL</BuildingClassType>
		<BuildingType/>
	</Row>
	<Row>
		<CivilizationType>CIVILIZATION_MINOR</CivilizationType>
		<BuildingClassType>BUILDINGCLASS_MONTMICHEL</BuildingClassType>
		<BuildingType/>
	</Row>
	<Row>
		<CivilizationType>CIVILIZATION_BARBARIAN</CivilizationType>
		<BuildingClassType>BUILDINGCLASS_TABRIZ</BuildingClassType>
		<BuildingType/>
	</Row>
	<Row>
		<CivilizationType>CIVILIZATION_MINOR</CivilizationType>
		<BuildingClassType>BUILDINGCLASS_TABRIZ</BuildingClassType>
		<BuildingType/>
	</Row>
	<Row>
		<CivilizationType>CIVILIZATION_BARBARIAN</CivilizationType>
		<BuildingClassType>BUILDINGCLASS_MOGAO</BuildingClassType>
		<BuildingType/>
	</Row>
	<Row>
		<CivilizationType>CIVILIZATION_MINOR</CivilizationType>
		<BuildingClassType>BUILDINGCLASS_MOGAO</BuildingClassType>
		<BuildingType/>
	</Row>
	<Row>
		<CivilizationType>CIVILIZATION_BARBARIAN</CivilizationType>
		<BuildingClassType>BUILDINGCLASS_LONGMEN</BuildingClassType>
		<BuildingType/>
	</Row>
	<Row>
		<CivilizationType>CIVILIZATION_MINOR</CivilizationType>
		<BuildingClassType>BUILDINGCLASS_LONGMEN</BuildingClassType>
		<BuildingType/>
	</Row>
	<Row>
		<CivilizationType>CIVILIZATION_BARBARIAN</CivilizationType>
		<BuildingClassType>BUILDINGCLASS_MINJAM</BuildingClassType>
		<BuildingType/>
	</Row>
	<Row>
		<CivilizationType>CIVILIZATION_MINOR</CivilizationType>
		<BuildingClassType>BUILDINGCLASS_MINJAM</BuildingClassType>
		<BuildingType/>
	</Row>
	<Row>
		<CivilizationType>CIVILIZATION_BARBARIAN</CivilizationType>
		<BuildingClassType>BUILDINGCLASS_STELZENDORF</BuildingClassType>
		<BuildingType/>
	</Row>
	<Row>
		<CivilizationType>CIVILIZATION_MINOR</CivilizationType>
		<BuildingClassType>BUILDINGCLASS_STELZENDORF</BuildingClassType>
		<BuildingType/>
	</Row>
	<Row>
		<CivilizationType>CIVILIZATION_BARBARIAN</CivilizationType>
		<BuildingClassType>BUILDINGCLASS_BAHRI</BuildingClassType>
		<BuildingType/>
	</Row>
	<Row>
		<CivilizationType>CIVILIZATION_MINOR</CivilizationType>
		<BuildingClassType>BUILDINGCLASS_BAHRI</BuildingClassType>
		<BuildingType/>
	</Row>
	<Row>
		<CivilizationType>CIVILIZATION_BARBARIAN</CivilizationType>
		<BuildingClassType>BUILDINGCLASS_HATTUSA</BuildingClassType>
		<BuildingType/>
	</Row>
	<Row>
		<CivilizationType>CIVILIZATION_MINOR</CivilizationType>
		<BuildingClassType>BUILDINGCLASS_HATTUSA</BuildingClassType>
		<BuildingType/>
	</Row>
	<Row>
		<CivilizationType>CIVILIZATION_BARBARIAN</CivilizationType>
		<BuildingClassType>BUILDINGCLASS_MOHENJO</BuildingClassType>
		<BuildingType/>
	</Row>
	<Row>
		<CivilizationType>CIVILIZATION_MINOR</CivilizationType>
		<BuildingClassType>BUILDINGCLASS_MOHENJO</BuildingClassType>
		<BuildingType/>
	</Row>
	<Row>
		<CivilizationType>CIVILIZATION_BARBARIAN</CivilizationType>
		<BuildingClassType>BUILDINGCLASS_PRAMBANAN</BuildingClassType>
		<BuildingType/>
	</Row>
	<Row>
		<CivilizationType>CIVILIZATION_MINOR</CivilizationType>
		<BuildingClassType>BUILDINGCLASS_PRAMBANAN</BuildingClassType>
		<BuildingType/>
	</Row>
	<Row>
		<CivilizationType>CIVILIZATION_BARBARIAN</CivilizationType>
		<BuildingClassType>BUILDINGCLASS_ELLORA</BuildingClassType>
		<BuildingType/>
	</Row>
	<Row>
		<CivilizationType>CIVILIZATION_MINOR</CivilizationType>
		<BuildingClassType>BUILDINGCLASS_ELLORA</BuildingClassType>
		<BuildingType/>
	</Row>
	<Row>
		<CivilizationType>CIVILIZATION_BARBARIAN</CivilizationType>
		<BuildingClassType>BUILDINGCLASS_NEWGRANGE</BuildingClassType>
		<BuildingType/>
	</Row>
	<Row>
		<CivilizationType>CIVILIZATION_MINOR</CivilizationType>
		<BuildingClassType>BUILDINGCLASS_NEWGRANGE</BuildingClassType>
		<BuildingType/>
	</Row>
	<Row>
		<CivilizationType>CIVILIZATION_BARBARIAN</CivilizationType>
		<BuildingClassType>BUILDINGCLASS_BENHADDOU</BuildingClassType>
		<BuildingType/>
	</Row>
	<Row>
		<CivilizationType>CIVILIZATION_MINOR</CivilizationType>
		<BuildingClassType>BUILDINGCLASS_BENHADDOU</BuildingClassType>
		<BuildingType/>
	</Row>
	<Row>
		<CivilizationType>CIVILIZATION_BARBARIAN</CivilizationType>
		<BuildingClassType>BUILDINGCLASS_MOGAO</BuildingClassType>
		<BuildingType/>
	</Row>
	<Row>
		<CivilizationType>CIVILIZATION_MINOR</CivilizationType>
		<BuildingClassType>BUILDINGCLASS_MOGAO</BuildingClassType>
		<BuildingType/>
	</Row>
	<Row>
		<CivilizationType>CIVILIZATION_BARBARIAN</CivilizationType>
		<BuildingClassType>BUILDINGCLASS_BARNENEZ</BuildingClassType>
		<BuildingType/>
	</Row>
	<Row>
		<CivilizationType>CIVILIZATION_MINOR</CivilizationType>
		<BuildingClassType>BUILDINGCLASS_BARNENEZ</BuildingClassType>
		<BuildingType/>
	</Row>
	<Row>
		<CivilizationType>CIVILIZATION_BARBARIAN</CivilizationType>
		<BuildingClassType>BUILDINGCLASS_COLOGNE</BuildingClassType>
		<BuildingType/>
	</Row>
	<Row>
		<CivilizationType>CIVILIZATION_MINOR</CivilizationType>
		<BuildingClassType>BUILDINGCLASS_COLOGNE</BuildingClassType>
		<BuildingType/>
	</Row>
	<Row>
		<CivilizationType>CIVILIZATION_BARBARIAN</CivilizationType>
		<BuildingClassType>BUILDINGCLASS_WONDERWERK</BuildingClassType>
		<BuildingType/>
	</Row>
	<Row>
		<CivilizationType>CIVILIZATION_MINOR</CivilizationType>
		<BuildingClassType>BUILDINGCLASS_WONDERWERK</BuildingClassType>
		<BuildingType/>
	</Row>
	<Row>
		<CivilizationType>CIVILIZATION_BARBARIAN</CivilizationType>
		<BuildingClassType>BUILDINGCLASS_HOLLYWOOD</BuildingClassType>
		<BuildingType/>
	</Row>
	<Row>
		<CivilizationType>CIVILIZATION_MINOR</CivilizationType>
		<BuildingClassType>BUILDINGCLASS_HOLLYWOOD</BuildingClassType>
		<BuildingType/>
	</Row>
	<Row>
		<CivilizationType>CIVILIZATION_BARBARIAN</CivilizationType>
		<BuildingClassType>BUILDINGCLASS_FREEDOMTOWER</BuildingClassType>
		<BuildingType/>
	</Row>
	<Row>
		<CivilizationType>CIVILIZATION_MINOR</CivilizationType>
		<BuildingClassType>BUILDINGCLASS_FREEDOMTOWER</BuildingClassType>
		<BuildingType/>
	</Row>
		<Row>
			<CivilizationType>CIVILIZATION_BARBARIAN</CivilizationType>
			<BuildingClassType>BUILDINGCLASS_THEOPETRACAVE</BuildingClassType>
			<BuildingType/>
		</Row>
		<Row>
			<CivilizationType>CIVILIZATION_MINOR</CivilizationType>
			<BuildingClassType>BUILDINGCLASS_THEOPETRACAVE</BuildingClassType>
			<BuildingType/>
		</Row>
		<Row>
			<CivilizationType>CIVILIZATION_BARBARIAN</CivilizationType>
			<BuildingClassType>BUILDINGCLASS_STAMM</BuildingClassType>
			<BuildingType/>
		</Row>
		<Row>
			<CivilizationType>CIVILIZATION_MINOR</CivilizationType>
			<BuildingClassType>BUILDINGCLASS_STAMM</BuildingClassType>
			<BuildingType/>
		</Row>
		<Row>
			<CivilizationType>CIVILIZATION_BARBARIAN</CivilizationType>
			<BuildingClassType>BUILDINGCLASS_UNITED_NATIONS_HQ</BuildingClassType>
			<BuildingType/>
		</Row>
		<Row>
			<CivilizationType>CIVILIZATION_MINOR</CivilizationType>
			<BuildingClassType>BUILDINGCLASS_UNITED_NATIONS_HQ</BuildingClassType>
			<BuildingType/>
		</Row>
		<Row>
			<CivilizationType>CIVILIZATION_BARBARIAN</CivilizationType>
			<BuildingClassType>BUILDINGCLASS_LONDON_ARRAY</BuildingClassType>
			<BuildingType/>
		</Row>
		<Row>
			<CivilizationType>CIVILIZATION_MINOR</CivilizationType>
			<BuildingClassType>BUILDINGCLASS_LONDON_ARRAY</BuildingClassType>
			<BuildingType/>
		</Row>
		<Row>
			<CivilizationType>CIVILIZATION_BARBARIAN</CivilizationType>
			<BuildingClassType>BUILDINGCLASS_PERGAMON</BuildingClassType>
			<BuildingType/>
		</Row>
		<Row>
			<CivilizationType>CIVILIZATION_MINOR</CivilizationType>
			<BuildingClassType>BUILDINGCLASS_PERGAMON</BuildingClassType>
			<BuildingType/>
		</Row>
		<Row>
			<CivilizationType>CIVILIZATION_BARBARIAN</CivilizationType>
			<BuildingClassType>BUILDINGCLASS_GARD</BuildingClassType>
			<BuildingType/>
		</Row>
		<Row>
			<CivilizationType>CIVILIZATION_MINOR</CivilizationType>
			<BuildingClassType>BUILDINGCLASS_GARD</BuildingClassType>
			<BuildingType/>
		</Row>
		<Row>
			<CivilizationType>CIVILIZATION_BARBARIAN</CivilizationType>
			<BuildingClassType>BUILDINGCLASS_ABU</BuildingClassType>
			<BuildingType/>
		</Row>
		<Row>
			<CivilizationType>CIVILIZATION_MINOR</CivilizationType>
			<BuildingClassType>BUILDINGCLASS_ABU</BuildingClassType>
			<BuildingType/>
		</Row>
		<Row>
			<CivilizationType>CIVILIZATION_BARBARIAN</CivilizationType>
			<BuildingClassType>BUILDINGCLASS_KASHI</BuildingClassType>
			<BuildingType/>
		</Row>
		<Row>
			<CivilizationType>CIVILIZATION_MINOR</CivilizationType>
			<BuildingClassType>BUILDINGCLASS_KASHI</BuildingClassType>
			<BuildingType/>
		</Row>
		<Row>
			<CivilizationType>CIVILIZATION_BARBARIAN</CivilizationType>
			<BuildingClassType>BUILDINGCLASS_TODAIJI</BuildingClassType>
			<BuildingType/>
		</Row>
		<Row>
			<CivilizationType>CIVILIZATION_MINOR</CivilizationType>
			<BuildingClassType>BUILDINGCLASS_TODAIJI</BuildingClassType>
			<BuildingType/>
		</Row>
		<Row>
			<CivilizationType>CIVILIZATION_BARBARIAN</CivilizationType>
			<BuildingClassType>BUILDINGCLASS_SMITHSONIAN</BuildingClassType>
			<BuildingType/>
		</Row>
		<Row>
			<CivilizationType>CIVILIZATION_MINOR</CivilizationType>
			<BuildingClassType>BUILDINGCLASS_SMITHSONIAN</BuildingClassType>
			<BuildingType/>
		</Row>
		<Row>
			<CivilizationType>CIVILIZATION_BARBARIAN</CivilizationType>
			<BuildingClassType>BUILDINGCLASS_EXODUS</BuildingClassType>
			<BuildingType/>
		</Row>
		<Row>
			<CivilizationType>CIVILIZATION_MINOR</CivilizationType>
			<BuildingClassType>BUILDINGCLASS_EXODUS</BuildingClassType>
			<BuildingType/>
		</Row>
		<Row>
			<CivilizationType>CIVILIZATION_BARBARIAN</CivilizationType>
			<BuildingClassType>BUILDINGCLASS_YANGTZE</BuildingClassType>
			<BuildingType/>
		</Row>
		<Row>
			<CivilizationType>CIVILIZATION_MINOR</CivilizationType>
			<BuildingClassType>BUILDINGCLASS_YANGTZE</BuildingClassType>
			<BuildingType/>
		</Row>
		<Row>
			<CivilizationType>CIVILIZATION_BARBARIAN</CivilizationType>
			<BuildingClassType>BUILDINGCLASS_CARNIVAL</BuildingClassType>
			<BuildingType/>
		</Row>
		<Row>
			<CivilizationType>CIVILIZATION_MINOR</CivilizationType>
			<BuildingClassType>BUILDINGCLASS_CARNIVAL</BuildingClassType>
			<BuildingType/>
		</Row>
		<Row>
			<CivilizationType>CIVILIZATION_BARBARIAN</CivilizationType>
			<BuildingClassType>BUILDINGCLASS_BERLINER_MAUER</BuildingClassType>
			<BuildingType/>
		</Row>
		<Row>
			<CivilizationType>CIVILIZATION_MINOR</CivilizationType>
			<BuildingClassType>BUILDINGCLASS_BERLINER_MAUER</BuildingClassType>
			<BuildingType/>
		</Row>
		<Row>
			<CivilizationType>CIVILIZATION_BARBARIAN</CivilizationType>
			<BuildingClassType>BUILDINGCLASS_EMPIRE</BuildingClassType>
			<BuildingType/>
		</Row>
		<Row>
			<CivilizationType>CIVILIZATION_MINOR</CivilizationType>
			<BuildingClassType>BUILDINGCLASS_EMPIRE</BuildingClassType>
			<BuildingType/>
		</Row>
		<Row>
			<CivilizationType>CIVILIZATION_BARBARIAN</CivilizationType>
			<BuildingClassType>BUILDINGCLASS_RUSHMORE</BuildingClassType>
			<BuildingType/>
		</Row>
		<Row>
			<CivilizationType>CIVILIZATION_MINOR</CivilizationType>
			<BuildingClassType>BUILDINGCLASS_RUSHMORE</BuildingClassType>
			<BuildingType/>
		</Row>
		<Row>
			<CivilizationType>CIVILIZATION_BARBARIAN</CivilizationType>
			<BuildingClassType>BUILDINGCLASS_TERRACES</BuildingClassType>
			<BuildingType/>
		</Row>
		<Row>
			<CivilizationType>CIVILIZATION_MINOR</CivilizationType>
			<BuildingClassType>BUILDINGCLASS_TERRACES</BuildingClassType>
			<BuildingType/>
		</Row>
		<Row>
			<CivilizationType>CIVILIZATION_BARBARIAN</CivilizationType>
			<BuildingClassType>BUILDINGCLASS_SILO</BuildingClassType>
			<BuildingType/>
		</Row>
		<Row>
			<CivilizationType>CIVILIZATION_MINOR</CivilizationType>
			<BuildingClassType>BUILDINGCLASS_SILO</BuildingClassType>
			<BuildingType/>
		</Row>
		<Row>
			<CivilizationType>CIVILIZATION_BARBARIAN</CivilizationType>
			<BuildingClassType>BUILDINGCLASS_MUSIK</BuildingClassType>
			<BuildingType/>
		</Row>
		<Row>
			<CivilizationType>CIVILIZATION_MINOR</CivilizationType>
			<BuildingClassType>BUILDINGCLASS_MUSIK</BuildingClassType>
			<BuildingType/>
		</Row>
		<Row>
			<CivilizationType>CIVILIZATION_BARBARIAN</CivilizationType>
			<BuildingClassType>BUILDINGCLASS_ITSUKUSHIMA</BuildingClassType>
			<BuildingType/>
		</Row>
		<Row>
			<CivilizationType>CIVILIZATION_MINOR</CivilizationType>
			<BuildingClassType>BUILDINGCLASS_ITSUKUSHIMA</BuildingClassType>
			<BuildingType/>
		</Row>
		<Row>
			<CivilizationType>CIVILIZATION_BARBARIAN</CivilizationType>
			<BuildingClassType>BUILDINGCLASS_IMPERIALER_GERICHTSHOF</BuildingClassType>
			<BuildingType/>
		</Row>
		<Row>
			<CivilizationType>CIVILIZATION_MINOR</CivilizationType>
			<BuildingClassType>BUILDINGCLASS_IMPERIALER_GERICHTSHOF</BuildingClassType>
			<BuildingType/>
		</Row>
		<Row>
			<CivilizationType>CIVILIZATION_BARBARIAN</CivilizationType>
			<BuildingClassType>BUILDINGCLASS_HANDLER</BuildingClassType>
			<BuildingType/>
		</Row>
		<Row>
			<CivilizationType>CIVILIZATION_MINOR</CivilizationType>
			<BuildingClassType>BUILDINGCLASS_HANDLER</BuildingClassType>
			<BuildingType/>
		</Row>
		<Row>
			<CivilizationType>CIVILIZATION_BARBARIAN</CivilizationType>
			<BuildingClassType>BUILDINGCLASS_GOLDEN_PAVILION</BuildingClassType>
			<BuildingType/>
		</Row>
		<Row>
			<CivilizationType>CIVILIZATION_MINOR</CivilizationType>
			<BuildingClassType>BUILDINGCLASS_GOLDEN_PAVILION</BuildingClassType>
			<BuildingType/>
		</Row>
		<Row>
			<CivilizationType>CIVILIZATION_BARBARIAN</CivilizationType>
			<BuildingClassType>BUILDINGCLASS_SKYTREE</BuildingClassType>
			<BuildingType/>
		</Row>
		<Row>
			<CivilizationType>CIVILIZATION_MINOR</CivilizationType>
			<BuildingClassType>BUILDINGCLASS_SKYTREE</BuildingClassType>
			<BuildingType/>
		</Row>
		<Row>
			<CivilizationType>CIVILIZATION_BARBARIAN</CivilizationType>
			<BuildingClassType>BUILDINGCLASS_VAULT</BuildingClassType>
			<BuildingType/>
		</Row>
		<Row>
			<CivilizationType>CIVILIZATION_MINOR</CivilizationType>
			<BuildingClassType>BUILDINGCLASS_VAULT</BuildingClassType>
			<BuildingType/>
		</Row>
		<Row>
			<CivilizationType>CIVILIZATION_BARBARIAN</CivilizationType>
			<BuildingClassType>BUILDINGCLASS_JELLING</BuildingClassType>
			<BuildingType/>
		</Row>
		<Row>
			<CivilizationType>CIVILIZATION_MINOR</CivilizationType>
			<BuildingClassType>BUILDINGCLASS_JELLING</BuildingClassType>
			<BuildingType/>
		</Row>
		<Row>
			<CivilizationType>CIVILIZATION_BARBARIAN</CivilizationType>
			<BuildingClassType>BUILDINGCLASS_RED_CROSS</BuildingClassType>
			<BuildingType/>
		</Row>
		<Row>
			<CivilizationType>CIVILIZATION_MINOR</CivilizationType>
			<BuildingClassType>BUILDINGCLASS_RED_CROSS</BuildingClassType>
			<BuildingType/>
		</Row>
		<Row>
			<CivilizationType>CIVILIZATION_BARBARIAN</CivilizationType>
			<BuildingClassType>BUILDINGCLASS_METEORA</BuildingClassType>
			<BuildingType/>
		</Row>
		<Row>
			<CivilizationType>CIVILIZATION_MINOR</CivilizationType>
			<BuildingClassType>BUILDINGCLASS_METEORA</BuildingClassType>
			<BuildingType/>
		</Row>
		<Row>
			<CivilizationType>CIVILIZATION_BARBARIAN</CivilizationType>
			<BuildingClassType>BUILDINGCLASS_PENA</BuildingClassType>
			<BuildingType/>
		</Row>
		<Row>
			<CivilizationType>CIVILIZATION_MINOR</CivilizationType>
			<BuildingClassType>BUILDINGCLASS_PENA</BuildingClassType>
			<BuildingType/>
		</Row>
		<Row>
			<CivilizationType>CIVILIZATION_BARBARIAN</CivilizationType>
			<BuildingClassType>BUILDINGCLASS_MADOL</BuildingClassType>
			<BuildingType/>
		</Row>
		<Row>
			<CivilizationType>CIVILIZATION_MINOR</CivilizationType>
			<BuildingClassType>BUILDINGCLASS_MADOL</BuildingClassType>
			<BuildingType/>
		</Row>
		<Row>
			<CivilizationType>CIVILIZATION_BARBARIAN</CivilizationType>
			<BuildingClassType>BUILDINGCLASS_LONDON</BuildingClassType>
			<BuildingType/>
		</Row>
		<Row>
			<CivilizationType>CIVILIZATION_MINOR</CivilizationType>
			<BuildingClassType>BUILDINGCLASS_LONDON</BuildingClassType>
			<BuildingType/>
		</Row>
		<Row>
			<CivilizationType>CIVILIZATION_BARBARIAN</CivilizationType>
			<BuildingClassType>BUILDINGCLASS_GATEWAY</BuildingClassType>
			<BuildingType/>
		</Row>
		<Row>
			<CivilizationType>CIVILIZATION_MINOR</CivilizationType>
			<BuildingClassType>BUILDINGCLASS_GATEWAY</BuildingClassType>
			<BuildingType/>
		</Row>
		<Row>
			<CivilizationType>CIVILIZATION_BARBARIAN</CivilizationType>
			<BuildingClassType>BUILDINGCLASS_SPUTNIK</BuildingClassType>
			<BuildingType/>
		</Row>
		<Row>
			<CivilizationType>CIVILIZATION_MINOR</CivilizationType>
			<BuildingClassType>BUILDINGCLASS_SPUTNIK</BuildingClassType>
			<BuildingType/>
		</Row>
		<Row>
			<CivilizationType>CIVILIZATION_BARBARIAN</CivilizationType>
			<BuildingClassType>BUILDINGCLASS_POTALA</BuildingClassType>
			<BuildingType/>
		</Row>
		<Row>
			<CivilizationType>CIVILIZATION_MINOR</CivilizationType>
			<BuildingClassType>BUILDINGCLASS_POTALA</BuildingClassType>
			<BuildingType/>
		</Row>
		<Row>
			<CivilizationType>CIVILIZATION_BARBARIAN</CivilizationType>
			<BuildingClassType>BUILDINGCLASS_TOPKAPI</BuildingClassType>
			<BuildingType/>
		</Row>
		<Row>
			<CivilizationType>CIVILIZATION_MINOR</CivilizationType>
			<BuildingClassType>BUILDINGCLASS_TOPKAPI</BuildingClassType>
			<BuildingType/>
		</Row>
		<Row>
			<CivilizationType>CIVILIZATION_BARBARIAN</CivilizationType>
			<BuildingClassType>BUILDINGCLASS_PETRONAS</BuildingClassType>
			<BuildingType/>
		</Row>
		<Row>
			<CivilizationType>CIVILIZATION_MINOR</CivilizationType>
			<BuildingClassType>BUILDINGCLASS_PETRONAS</BuildingClassType>
			<BuildingType/>
		</Row>
		<Row>
			<CivilizationType>CIVILIZATION_BARBARIAN</CivilizationType>
			<BuildingClassType>BUILDINGCLASS_WARTBURG</BuildingClassType>
			<BuildingType/>
		</Row>
		<Row>
			<CivilizationType>CIVILIZATION_MINOR</CivilizationType>
			<BuildingClassType>BUILDINGCLASS_WARTBURG</BuildingClassType>
			<BuildingType/>
		</Row>
		<Row>
			<CivilizationType>CIVILIZATION_BARBARIAN</CivilizationType>
			<BuildingClassType>BUILDINGCLASS_MESAVERDE</BuildingClassType>
			<BuildingType/>
		</Row>
		<Row>
			<CivilizationType>CIVILIZATION_MINOR</CivilizationType>
			<BuildingClassType>BUILDINGCLASS_MESAVERDE</BuildingClassType>
			<BuildingType/>
		</Row>
		<Row>
			<CivilizationType>CIVILIZATION_BARBARIAN</CivilizationType>
			<BuildingClassType>BUILDINGCLASS_TAJIN</BuildingClassType>
			<BuildingType/>
		</Row>
		<Row>
			<CivilizationType>CIVILIZATION_MINOR</CivilizationType>
			<BuildingClassType>BUILDINGCLASS_TAJIN</BuildingClassType>
			<BuildingType/>
		</Row>
		<Row>
			<CivilizationType>CIVILIZATION_BARBARIAN</CivilizationType>
			<BuildingClassType>BUILDINGCLASS_GOBEKLI</BuildingClassType>
			<BuildingType/>
		</Row>
		<Row>
			<CivilizationType>CIVILIZATION_MINOR</CivilizationType>
			<BuildingClassType>BUILDINGCLASS_GOBEKLI</BuildingClassType>
			<BuildingType/>
		</Row>
		<Row>
			<CivilizationType>CIVILIZATION_BARBARIAN</CivilizationType>
			<BuildingClassType>BUILDINGCLASS_BABEL</BuildingClassType>
			<BuildingType/>
		</Row>
		<Row>
			<CivilizationType>CIVILIZATION_BARBARIAN</CivilizationType>
			<BuildingClassType>BUILDINGCLASS_TAIPEI</BuildingClassType>
			<BuildingType/>
		</Row>
		<Row>
			<CivilizationType>CIVILIZATION_MINOR</CivilizationType>
			<BuildingClassType>BUILDINGCLASS_TAIPEI</BuildingClassType>
			<BuildingType/>
		</Row>
		<Row>
			<CivilizationType>CIVILIZATION_MINOR</CivilizationType>
			<BuildingClassType>BUILDINGCLASS_BABEL</BuildingClassType>
			<BuildingType/>
		</Row>
		<Row>
			<CivilizationType>CIVILIZATION_BARBARIAN</CivilizationType>
			<BuildingClassType>BUILDINGCLASS_BROOKLYN</BuildingClassType>
			<BuildingType/>
		</Row>
		<Row>
			<CivilizationType>CIVILIZATION_MINOR</CivilizationType>
			<BuildingClassType>BUILDINGCLASS_BROOKLYN</BuildingClassType>
			<BuildingType/>
		</Row>
		<Row>
			<CivilizationType>CIVILIZATION_BARBARIAN</CivilizationType>
			<BuildingClassType>BUILDINGCLASS_MILLAU</BuildingClassType>
			<BuildingType/>
		</Row>
		<Row>
			<CivilizationType>CIVILIZATION_MINOR</CivilizationType>
			<BuildingClassType>BUILDINGCLASS_MILLAU</BuildingClassType>
			<BuildingType/>
		</Row>
		<Row>
			<CivilizationType>CIVILIZATION_BARBARIAN</CivilizationType>
			<BuildingClassType>BUILDINGCLASS_DARJEELING</BuildingClassType>
			<BuildingType/>
		</Row>
		<Row>
			<CivilizationType>CIVILIZATION_MINOR</CivilizationType>
			<BuildingClassType>BUILDINGCLASS_DARJEELING</BuildingClassType>
			<BuildingType/>
		</Row>
		<Row>
			<CivilizationType>CIVILIZATION_BARBARIAN</CivilizationType>
			<BuildingClassType>BUILDINGCLASS_GRIPSHOLM</BuildingClassType>
			<BuildingType/>
		</Row>
		<Row>
			<CivilizationType>CIVILIZATION_MINOR</CivilizationType>
			<BuildingClassType>BUILDINGCLASS_GRIPSHOLM</BuildingClassType>
			<BuildingType/>
		</Row>
		<Row>
			<CivilizationType>CIVILIZATION_BARBARIAN</CivilizationType>
			<BuildingClassType>BUILDINGCLASS_ARECIBO</BuildingClassType>
			<BuildingType/>
		</Row>
		<Row>
			<CivilizationType>CIVILIZATION_MINOR</CivilizationType>
			<BuildingClassType>BUILDINGCLASS_ARECIBO</BuildingClassType>
			<BuildingType/>
		</Row>
		<Row>
			<CivilizationType>CIVILIZATION_BARBARIAN</CivilizationType>
			<BuildingClassType>BUILDINGCLASS_MLK</BuildingClassType>
			<BuildingType/>
		</Row>
		<Row>
			<CivilizationType>CIVILIZATION_MINOR</CivilizationType>
			<BuildingClassType>BUILDINGCLASS_MLK</BuildingClassType>
			<BuildingType/>
		</Row>
		<Row>
			<CivilizationType>CIVILIZATION_BARBARIAN</CivilizationType>
			<BuildingClassType>BUILDINGCLASS_WHITESANDS</BuildingClassType>
			<BuildingType/>
		</Row>
		<Row>
			<CivilizationType>CIVILIZATION_MINOR</CivilizationType>
			<BuildingClassType>BUILDINGCLASS_WHITESANDS</BuildingClassType>
			<BuildingType/>
		</Row>
		<Row>
			<CivilizationType>CIVILIZATION_BARBARIAN</CivilizationType>
			<BuildingClassType>BUILDINGCLASS_PANAMA</BuildingClassType>
			<BuildingType/>
		</Row>
		<Row>
			<CivilizationType>CIVILIZATION_MINOR</CivilizationType>
			<BuildingClassType>BUILDINGCLASS_PANAMA</BuildingClassType>
			<BuildingType/>
		</Row>
		<Row>
			<CivilizationType>CIVILIZATION_BARBARIAN</CivilizationType>
			<BuildingClassType>BUILDINGCLASS_TEMPLO</BuildingClassType>
			<BuildingType/>
		</Row>
		<Row>
			<CivilizationType>CIVILIZATION_MINOR</CivilizationType>
			<BuildingClassType>BUILDINGCLASS_TEMPLO</BuildingClassType>
			<BuildingType/>
		</Row>
		<Row>
			<CivilizationType>CIVILIZATION_BARBARIAN</CivilizationType>
			<BuildingClassType>BUILDINGCLASS_TOTEM</BuildingClassType>
			<BuildingType/>
		</Row>
		<Row>
			<CivilizationType>CIVILIZATION_MINOR</CivilizationType>
			<BuildingClassType>BUILDINGCLASS_TOTEM</BuildingClassType>
			<BuildingType/>
		</Row>
		<Row>
			<CivilizationType>CIVILIZATION_BARBARIAN</CivilizationType>
			<BuildingClassType>BUILDINGCLASS_TEOTIHUACAN</BuildingClassType>
			<BuildingType/>
		</Row>
		<Row>
			<CivilizationType>CIVILIZATION_MINOR</CivilizationType>
			<BuildingClassType>BUILDINGCLASS_TEOTIHUACAN</BuildingClassType>
			<BuildingType/>
		</Row>
		<Row>
			<CivilizationType>CIVILIZATION_BARBARIAN</CivilizationType>
			<BuildingClassType>BUILDINGCLASS_STONE_TOWN</BuildingClassType>
			<BuildingType/>
		</Row>
		<Row>
			<CivilizationType>CIVILIZATION_MINOR</CivilizationType>
			<BuildingClassType>BUILDINGCLASS_STONE_TOWN</BuildingClassType>
			<BuildingType/>
		</Row>
		<Row>
			<CivilizationType>CIVILIZATION_BARBARIAN</CivilizationType>
			<BuildingClassType>BUILDINGCLASS_HAJI_ALI_DARGAH</BuildingClassType>
			<BuildingType/>
		</Row>
		<Row>
			<CivilizationType>CIVILIZATION_MINOR</CivilizationType>
			<BuildingClassType>BUILDINGCLASS_HAJI_ALI_DARGAH</BuildingClassType>
			<BuildingType/>
		</Row>
		<Row>
			<CivilizationType>CIVILIZATION_BARBARIAN</CivilizationType>
			<BuildingClassType>BUILDINGCLASS_ISHTAR</BuildingClassType>
			<BuildingType/>
		</Row>
		<Row>
			<CivilizationType>CIVILIZATION_MINOR</CivilizationType>
			<BuildingClassType>BUILDINGCLASS_ISHTAR</BuildingClassType>
			<BuildingType/>
		</Row>
		<Row>
			<CivilizationType>CIVILIZATION_BARBARIAN</CivilizationType>
			<BuildingClassType>BUILDINGCLASS_CAPITOL</BuildingClassType>
			<BuildingType/>
		</Row>
		<Row>
			<CivilizationType>CIVILIZATION_MINOR</CivilizationType>
			<BuildingClassType>BUILDINGCLASS_CAPITOL</BuildingClassType>
			<BuildingType/>
		</Row>
		<Row>
			<CivilizationType>CIVILIZATION_BARBARIAN</CivilizationType>
			<BuildingClassType>BUILDINGCLASS_GOLDENGATE</BuildingClassType>
			<BuildingType/>
		</Row>
		<Row>
			<CivilizationType>CIVILIZATION_MINOR</CivilizationType>
			<BuildingClassType>BUILDINGCLASS_GOLDENGATE</BuildingClassType>
			<BuildingType/>
		</Row>
		<Row>
			<CivilizationType>CIVILIZATION_BARBARIAN</CivilizationType>
			<BuildingClassType>BUILDINGCLASS_TITICACA</BuildingClassType>
			<BuildingType/>
		</Row>
		<Row>
			<CivilizationType>CIVILIZATION_MINOR</CivilizationType>
			<BuildingClassType>BUILDINGCLASS_TITICACA</BuildingClassType>
			<BuildingType/>
		</Row>
		<Row>
			<CivilizationType>CIVILIZATION_BARBARIAN</CivilizationType>
			<BuildingClassType>BUILDINGCLASS_TAHRIR</BuildingClassType>
			<BuildingType/>
		</Row>
		<Row>
			<CivilizationType>CIVILIZATION_MINOR</CivilizationType>
			<BuildingClassType>BUILDINGCLASS_TAHRIR</BuildingClassType>
			<BuildingType/>
		</Row>
		<Row>
			<CivilizationType>CIVILIZATION_BARBARIAN</CivilizationType>
			<BuildingClassType>BUILDINGCLASS_MARTYRS</BuildingClassType>
			<BuildingType/>
		</Row>
		<Row>
			<CivilizationType>CIVILIZATION_MINOR</CivilizationType>
			<BuildingClassType>BUILDINGCLASS_MARTYRS</BuildingClassType>
			<BuildingType/>
		</Row>
		<Row>
			<CivilizationType>CIVILIZATION_BARBARIAN</CivilizationType>
			<BuildingClassType>BUILDINGCLASS_PEARL_MONUMENT</BuildingClassType>
			<BuildingType/>
		</Row>
		<Row>
			<CivilizationType>CIVILIZATION_MINOR</CivilizationType>
			<BuildingClassType>BUILDINGCLASS_PEARL_MONUMENT</BuildingClassType>
			<BuildingType/>
		</Row>
		<Row>
			<CivilizationType>CIVILIZATION_BARBARIAN</CivilizationType>
			<BuildingClassType>BUILDINGCLASS_HABIB_BOURGUIBA</BuildingClassType>
			<BuildingType/>
		</Row>
		<Row>
			<CivilizationType>CIVILIZATION_MINOR</CivilizationType>
			<BuildingClassType>BUILDINGCLASS_HABIB_BOURGUIBA</BuildingClassType>
			<BuildingType/>
		</Row>
		<Row>
			<CivilizationType>CIVILIZATION_BARBARIAN</CivilizationType>
			<BuildingClassType>BUILDINGCLASS_SELARON</BuildingClassType>
			<BuildingType/>
		</Row>
		<Row>
			<CivilizationType>CIVILIZATION_BARBARIAN</CivilizationType>
			<BuildingClassType>BUILDINGCLASS_PALM</BuildingClassType>
			<BuildingType/>
		</Row>
		<Row>
			<CivilizationType>CIVILIZATION_MINOR</CivilizationType>
			<BuildingClassType>BUILDINGCLASS_PALM</BuildingClassType>
			<BuildingType/>
		</Row>
		<Row>
			<CivilizationType>CIVILIZATION_MINOR</CivilizationType>
			<BuildingClassType>BUILDINGCLASS_SELARON</BuildingClassType>
			<BuildingType/>
		</Row>
		<Row>
			<CivilizationType>CIVILIZATION_BARBARIAN</CivilizationType>
			<BuildingClassType>BUILDINGCLASS_WATPHRAKAEW</BuildingClassType>
			<BuildingType/>
		</Row>
		<Row>
			<CivilizationType>CIVILIZATION_MINOR</CivilizationType>
			<BuildingClassType>BUILDINGCLASS_WATPHRAKAEW</BuildingClassType>
			<BuildingType/>
		</Row>
		<Row>
			<CivilizationType>CIVILIZATION_BARBARIAN</CivilizationType>
			<BuildingClassType>BUILDINGCLASS_YELLOW_CRANE</BuildingClassType>
			<BuildingType/>
		</Row>
		<Row>
			<CivilizationType>CIVILIZATION_BARBARIAN</CivilizationType>
			<BuildingClassType>BUILDINGCLASS_DOGESPALACE</BuildingClassType>
			<BuildingType/>
		</Row>
		<Row>
			<CivilizationType>CIVILIZATION_MINOR</CivilizationType>
			<BuildingClassType>BUILDINGCLASS_DOGESPALACE</BuildingClassType>
			<BuildingType/>
		</Row>
		<Row>
			<CivilizationType>CIVILIZATION_MINOR</CivilizationType>
			<BuildingClassType>BUILDINGCLASS_YELLOW_CRANE</BuildingClassType>
			<BuildingType/>
		</Row>
		<Row>
			<CivilizationType>CIVILIZATION_BARBARIAN</CivilizationType>
			<BuildingClassType>BUILDINGCLASS_XUANKONG</BuildingClassType>
			<BuildingType/>
		</Row>
		<Row>
			<CivilizationType>CIVILIZATION_MINOR</CivilizationType>
			<BuildingClassType>BUILDINGCLASS_XUANKONG</BuildingClassType>
			<BuildingType/>
		</Row>
		<Row>
			<CivilizationType>CIVILIZATION_BARBARIAN</CivilizationType>
			<BuildingClassType>BUILDINGCLASS_HORYUJI</BuildingClassType>
			<BuildingType/>
		</Row>
		<Row>
			<CivilizationType>CIVILIZATION_MINOR</CivilizationType>
			<BuildingClassType>BUILDINGCLASS_HORYUJI</BuildingClassType>
			<BuildingType/>
		</Row>
		<Row>
			<CivilizationType>CIVILIZATION_BARBARIAN</CivilizationType>
			<BuildingClassType>BUILDINGCLASS_SHANGHAI_WFC</BuildingClassType>
			<BuildingType/>
		</Row>
		<Row>
			<CivilizationType>CIVILIZATION_MINOR</CivilizationType>
			<BuildingClassType>BUILDINGCLASS_SHANGHAI_WFC</BuildingClassType>
			<BuildingType/>
		</Row>
		<Row>
			<CivilizationType>CIVILIZATION_BARBARIAN</CivilizationType>
			<BuildingClassType>BUILDINGCLASS_BUDA</BuildingClassType>
			<BuildingType/>
		</Row>
		<Row>
			<CivilizationType>CIVILIZATION_MINOR</CivilizationType>
			<BuildingClassType>BUILDINGCLASS_BUDA</BuildingClassType>
			<BuildingType/>
		</Row>
		<Row>
			<CivilizationType>CIVILIZATION_BARBARIAN</CivilizationType>
			<BuildingClassType>BUILDINGCLASS_JIAYUGUAN</BuildingClassType>
			<BuildingType/>
		</Row>
		<Row>
			<CivilizationType>CIVILIZATION_MINOR</CivilizationType>
			<BuildingClassType>BUILDINGCLASS_JIAYUGUAN</BuildingClassType>
			<BuildingType/>
		</Row>
		<Row>
			<CivilizationType>CIVILIZATION_BARBARIAN</CivilizationType>
			<BuildingClassType>BUILDINGCLASS_GULOU</BuildingClassType>
			<BuildingType/>
		</Row>
		<Row>
			<CivilizationType>CIVILIZATION_MINOR</CivilizationType>
			<BuildingClassType>BUILDINGCLASS_GULOU</BuildingClassType>
			<BuildingType/>
		</Row>
		<Row>
			<CivilizationType>CIVILIZATION_BARBARIAN</CivilizationType>
			<BuildingClassType>BUILDINGCLASS_GATE_SUN</BuildingClassType>
			<BuildingType/>
		</Row>
		<Row>
			<CivilizationType>CIVILIZATION_MINOR</CivilizationType>
			<BuildingClassType>BUILDINGCLASS_GATE_SUN</BuildingClassType>
			<BuildingType/>
		</Row>
		<Row>
			<CivilizationType>CIVILIZATION_BARBARIAN</CivilizationType>
			<BuildingClassType>BUILDINGCLASS_KNOSSOS</BuildingClassType>
			<BuildingType/>
		</Row>
		<Row>
			<CivilizationType>CIVILIZATION_MINOR</CivilizationType>
			<BuildingClassType>BUILDINGCLASS_KNOSSOS</BuildingClassType>
			<BuildingType/>
		</Row>
		<Row>
			<CivilizationType>CIVILIZATION_BARBARIAN</CivilizationType>
			<BuildingClassType>BUILDINGCLASS_LALIBELA</BuildingClassType>
			<BuildingType/>
		</Row>
		<Row>
			<CivilizationType>CIVILIZATION_MINOR</CivilizationType>
			<BuildingClassType>BUILDINGCLASS_LALIBELA</BuildingClassType>
			<BuildingType/>
		</Row>
		<Row>
			<CivilizationType>CIVILIZATION_BARBARIAN</CivilizationType>
			<BuildingClassType>BUILDINGCLASS_TORRE</BuildingClassType>
			<BuildingType/>
		</Row>
		<Row>
			<CivilizationType>CIVILIZATION_MINOR</CivilizationType>
			<BuildingClassType>BUILDINGCLASS_TORRE</BuildingClassType>
			<BuildingType/>
		</Row>
		<Row>
			<CivilizationType>CIVILIZATION_BARBARIAN</CivilizationType>
			<BuildingClassType>BUILDINGCLASS_TAKTSANG</BuildingClassType>
			<BuildingType/>
		</Row>
		<Row>
			<CivilizationType>CIVILIZATION_MINOR</CivilizationType>
			<BuildingClassType>BUILDINGCLASS_TAKTSANG</BuildingClassType>
			<BuildingType/>
		</Row>
		<Row>
			<CivilizationType>CIVILIZATION_BARBARIAN</CivilizationType>
			<BuildingClassType>BUILDINGCLASS_LESHAN</BuildingClassType>
			<BuildingType/>
		</Row>
		<Row>
			<CivilizationType>CIVILIZATION_MINOR</CivilizationType>
			<BuildingClassType>BUILDINGCLASS_LESHAN</BuildingClassType>
			<BuildingType/>
		</Row>
		<Row>
			<CivilizationType>CIVILIZATION_BARBARIAN</CivilizationType>
			<BuildingClassType>BUILDINGCLASS_HANSA</BuildingClassType>
			<BuildingType/>
		</Row>
		<Row>
			<CivilizationType>CIVILIZATION_MINOR</CivilizationType>
			<BuildingClassType>BUILDINGCLASS_HANSA</BuildingClassType>
			<BuildingType/>
		</Row>
		<Row>
			<CivilizationType>CIVILIZATION_BARBARIAN</CivilizationType>
			<BuildingClassType>BUILDINGCLASS_KASHI</BuildingClassType>
			<BuildingType/>
		</Row>
		<Row>
			<CivilizationType>CIVILIZATION_MINOR</CivilizationType>
			<BuildingClassType>BUILDINGCLASS_KASHI</BuildingClassType>
			<BuildingType/>
		</Row>
		<Row>
			<CivilizationType>CIVILIZATION_BARBARIAN</CivilizationType>
			<BuildingClassType>BUILDINGCLASS_KARNAK</BuildingClassType>
			<BuildingType/>
		</Row>
		<Row>
			<CivilizationType>CIVILIZATION_MINOR</CivilizationType>
			<BuildingClassType>BUILDINGCLASS_KARNAK</BuildingClassType>
			<BuildingType/>
		</Row>
		<Row>
			<CivilizationType>CIVILIZATION_BARBARIAN</CivilizationType>
			<BuildingClassType>BUILDINGCLASS_DOME</BuildingClassType>
			<BuildingType/>
		</Row>
		<Row>
			<CivilizationType>CIVILIZATION_MINOR</CivilizationType>
			<BuildingClassType>BUILDINGCLASS_DOME</BuildingClassType>
			<BuildingType/>
		</Row>
		<Row>
			<CivilizationType>CIVILIZATION_BARBARIAN</CivilizationType>
			<BuildingClassType>BUILDINGCLASS_BAMIYAN</BuildingClassType>
			<BuildingType/>
		</Row>
		<Row>
			<CivilizationType>CIVILIZATION_MINOR</CivilizationType>
			<BuildingClassType>BUILDINGCLASS_BAMIYAN</BuildingClassType>
			<BuildingType/>
		</Row>
		<Row>
			<CivilizationType>CIVILIZATION_BARBARIAN</CivilizationType>
			<BuildingClassType>BUILDINGCLASS_BANAUE</BuildingClassType>
			<BuildingType/>
		</Row>
		<Row>
			<CivilizationType>CIVILIZATION_MINOR</CivilizationType>
			<BuildingClassType>BUILDINGCLASS_BANAUE</BuildingClassType>
			<BuildingType/>
		</Row>
		<Row>
			<CivilizationType>CIVILIZATION_BARBARIAN</CivilizationType>
			<BuildingClassType>BUILDINGCLASS_SHIMIZUMCPCT</BuildingClassType>
			<BuildingType/>
		</Row>
		<Row>
			<CivilizationType>CIVILIZATION_MINOR</CivilizationType>
			<BuildingClassType>BUILDINGCLASS_SHIMIZUMCPCT</BuildingClassType>
			<BuildingType/>
		</Row>
		<Row>
			<CivilizationType>CIVILIZATION_BARBARIAN</CivilizationType>
			<BuildingClassType>BUILDINGCLASS_LAQROX</BuildingClassType>
			<BuildingType/>
		</Row>
		<Row>
			<CivilizationType>CIVILIZATION_MINOR</CivilizationType>
			<BuildingClassType>BUILDINGCLASS_LAQROX</BuildingClassType>
			<BuildingType/>
		</Row>
		<Row>
			<CivilizationType>CIVILIZATION_BARBARIAN</CivilizationType>
			<BuildingClassType>BUILDINGCLASS_HUETTE</BuildingClassType>
			<BuildingType/>
		</Row>
		<Row>
			<CivilizationType>CIVILIZATION_MINOR</CivilizationType>
			<BuildingClassType>BUILDINGCLASS_HUETTE</BuildingClassType>
			<BuildingType/>
		</Row>
		<Row>
			<CivilizationType>CIVILIZATION_BARBARIAN</CivilizationType>
			<BuildingClassType>BUILDINGCLASS_FLOATINGISLANDSCT</BuildingClassType>
			<BuildingType/>
		</Row>
		<Row>
			<CivilizationType>CIVILIZATION_MINOR</CivilizationType>
			<BuildingClassType>BUILDINGCLASS_FLOATINGISLANDSCT</BuildingClassType>
			<BuildingType/>
		</Row>
		<Row>
			<CivilizationType>CIVILIZATION_BARBARIAN</CivilizationType>
			<BuildingClassType>BUILDINGCLASS_SKYCITY</BuildingClassType>
			<BuildingType/>
		</Row>
		<Row>
			<CivilizationType>CIVILIZATION_MINOR</CivilizationType>
			<BuildingClassType>BUILDINGCLASS_SKYCITY</BuildingClassType>
			<BuildingType/>
		</Row>
		<Row>
			<CivilizationType>CIVILIZATION_BARBARIAN</CivilizationType>
			<BuildingClassType>BUILDINGCLASS_MATTERHORN</BuildingClassType>
			<BuildingType/>
		</Row>
		<Row>
			<CivilizationType>CIVILIZATION_MINOR</CivilizationType>
			<BuildingClassType>BUILDINGCLASS_MATTERHORN</BuildingClassType>
			<BuildingType/>
		</Row>
		<Row>
			<CivilizationType>CIVILIZATION_BARBARIAN</CivilizationType>
			<BuildingClassType>BUILDINGCLASS_HEDDAL</BuildingClassType>
			<BuildingType/>
		</Row>
		<Row>
			<CivilizationType>CIVILIZATION_MINOR</CivilizationType>
			<BuildingClassType>BUILDINGCLASS_HEDDAL</BuildingClassType>
			<BuildingType/>
		</Row>
		<Row>
			<CivilizationType>CIVILIZATION_BARBARIAN</CivilizationType>
			<BuildingClassType>BUILDINGCLASS_KALMAR</BuildingClassType>
			<BuildingType/>
		</Row>
		<Row>
			<CivilizationType>CIVILIZATION_MINOR</CivilizationType>
			<BuildingClassType>BUILDINGCLASS_KALMAR</BuildingClassType>
			<BuildingType/>
		</Row>
		<Row>
			<CivilizationType>CIVILIZATION_BARBARIAN</CivilizationType>
			<BuildingClassType>BUILDINGCLASS_SUOMENLINNA</BuildingClassType>
			<BuildingType/>
		</Row>
		<Row>
			<CivilizationType>CIVILIZATION_MINOR</CivilizationType>
			<BuildingClassType>BUILDINGCLASS_SUOMENLINNA</BuildingClassType>
			<BuildingType/>
		</Row>
		<Row>
			<CivilizationType>CIVILIZATION_BARBARIAN</CivilizationType>
			<BuildingClassType>BUILDINGCLASS_ROCKEFELLER</BuildingClassType>
			<BuildingType/>
		</Row>
		<Row>
			<CivilizationType>CIVILIZATION_MINOR</CivilizationType>
			<BuildingClassType>BUILDINGCLASS_ROCKEFELLER</BuildingClassType>
			<BuildingType/>
		</Row>
		<Row>
			<CivilizationType>CIVILIZATION_BARBARIAN</CivilizationType>
			<BuildingClassType>BUILDINGCLASS_TETII</BuildingClassType>
			<BuildingType/>
		</Row>
		<Row>
			<CivilizationType>CIVILIZATION_MINOR</CivilizationType>
			<BuildingClassType>BUILDINGCLASS_TETII</BuildingClassType>
			<BuildingType/>
		</Row>
		<Row>
			<CivilizationType>CIVILIZATION_BARBARIAN</CivilizationType>
			<BuildingClassType>BUILDINGCLASS_WEIYANG</BuildingClassType>
			<BuildingType/>
		</Row>
		<Row>
			<CivilizationType>CIVILIZATION_MINOR</CivilizationType>
			<BuildingClassType>BUILDINGCLASS_WEIYANG</BuildingClassType>
			<BuildingType/>
		</Row>
		<Row>
			<CivilizationType>CIVILIZATION_BARBARIAN</CivilizationType>
			<BuildingClassType>BUILDINGCLASS_SMITHSONIAN</BuildingClassType>
			<BuildingType/>
		</Row>
		<Row>
			<CivilizationType>CIVILIZATION_MINOR</CivilizationType>
			<BuildingClassType>BUILDINGCLASS_SMITHSONIAN</BuildingClassType>
			<BuildingType/>
		</Row>
		<Row>
			<CivilizationType>CIVILIZATION_BARBARIAN</CivilizationType>
			<BuildingClassType>BUILDINGCLASS_EXODUS</BuildingClassType>
			<BuildingType/>
		</Row>
		<Row>
			<CivilizationType>CIVILIZATION_MINOR</CivilizationType>
			<BuildingClassType>BUILDINGCLASS_EXODUS</BuildingClassType>
			<BuildingType/>
		</Row>
		<Row>
			<CivilizationType>CIVILIZATION_BARBARIAN</CivilizationType>
			<BuildingClassType>BUILDINGCLASS_YANGTZE</BuildingClassType>
			<BuildingType/>
		</Row>
		<Row>
			<CivilizationType>CIVILIZATION_MINOR</CivilizationType>
			<BuildingClassType>BUILDINGCLASS_YANGTZE</BuildingClassType>
			<BuildingType/>
		</Row>
		<Row>
			<CivilizationType>CIVILIZATION_BARBARIAN</CivilizationType>
			<BuildingClassType>BUILDINGCLASS_CARNIVAL</BuildingClassType>
			<BuildingType/>
		</Row>
		<Row>
			<CivilizationType>CIVILIZATION_MINOR</CivilizationType>
			<BuildingClassType>BUILDINGCLASS_CARNIVAL</BuildingClassType>
			<BuildingType/>
		</Row>
		<Row>
			<CivilizationType>CIVILIZATION_BARBARIAN</CivilizationType>
			<BuildingClassType>BUILDINGCLASS_BERLINER_MAUER</BuildingClassType>
			<BuildingType/>
		</Row>
		<Row>
			<CivilizationType>CIVILIZATION_MINOR</CivilizationType>
			<BuildingClassType>BUILDINGCLASS_BERLINER_MAUER</BuildingClassType>
			<BuildingType/>
		</Row>
		<Row>
			<CivilizationType>CIVILIZATION_BARBARIAN</CivilizationType>
			<BuildingClassType>BUILDINGCLASS_RUSHMORE</BuildingClassType>
			<BuildingType/>
		</Row>
		<Row>
			<CivilizationType>CIVILIZATION_MINOR</CivilizationType>
			<BuildingClassType>BUILDINGCLASS_RUSHMORE</BuildingClassType>
			<BuildingType/>
		</Row>
		<Row>
			<CivilizationType>CIVILIZATION_BARBARIAN</CivilizationType>
			<BuildingClassType>BUILDINGCLASS_TERRACES</BuildingClassType>
			<BuildingType/>
		</Row>
		<Row>
			<CivilizationType>CIVILIZATION_MINOR</CivilizationType>
			<BuildingClassType>BUILDINGCLASS_TERRACES</BuildingClassType>
			<BuildingType/>
		</Row>
		<Row>
			<CivilizationType>CIVILIZATION_BARBARIAN</CivilizationType>
			<BuildingClassType>BUILDINGCLASS_SILO</BuildingClassType>
			<BuildingType/>
		</Row>
		<Row>
			<CivilizationType>CIVILIZATION_MINOR</CivilizationType>
			<BuildingClassType>BUILDINGCLASS_SILO</BuildingClassType>
			<BuildingType/>
		</Row>
		<Row>
			<CivilizationType>CIVILIZATION_BARBARIAN</CivilizationType>
			<BuildingClassType>BUILDINGCLASS_MUSIK</BuildingClassType>
			<BuildingType/>
		</Row>
		<Row>
			<CivilizationType>CIVILIZATION_MINOR</CivilizationType>
			<BuildingClassType>BUILDINGCLASS_MUSIK</BuildingClassType>
			<BuildingType/>
		</Row>
		<Row>
			<CivilizationType>CIVILIZATION_BARBARIAN</CivilizationType>
			<BuildingClassType>BUILDINGCLASS_IMPERIALER_GERICHTSHOF</BuildingClassType>
			<BuildingType/>
		</Row>
		<Row>
			<CivilizationType>CIVILIZATION_MINOR</CivilizationType>
			<BuildingClassType>BUILDINGCLASS_IMPERIALER_GERICHTSHOF</BuildingClassType>
			<BuildingType/>
		</Row>
		<Row>
			<CivilizationType>CIVILIZATION_BARBARIAN</CivilizationType>
			<BuildingClassType>BUILDINGCLASS_HANDLER</BuildingClassType>
			<BuildingType/>
		</Row>
		<Row>
			<CivilizationType>CIVILIZATION_MINOR</CivilizationType>
			<BuildingClassType>BUILDINGCLASS_HANDLER</BuildingClassType>
			<BuildingType/>
		</Row>
		<Row>
			<CivilizationType>CIVILIZATION_BARBARIAN</CivilizationType>
			<BuildingClassType>BUILDINGCLASS_GOLDEN_PAVILION</BuildingClassType>
			<BuildingType/>
		</Row>
		<Row>
			<CivilizationType>CIVILIZATION_MINOR</CivilizationType>
			<BuildingClassType>BUILDINGCLASS_GOLDEN_PAVILION</BuildingClassType>
			<BuildingType/>
		</Row>
		<Row>
			<CivilizationType>CIVILIZATION_BARBARIAN</CivilizationType>
			<BuildingClassType>BUILDINGCLASS_VAULT</BuildingClassType>
			<BuildingType/>
		</Row>
		<Row>
			<CivilizationType>CIVILIZATION_MINOR</CivilizationType>
			<BuildingClassType>BUILDINGCLASS_VAULT</BuildingClassType>
			<BuildingType/>
		</Row>
		<Row>
			<CivilizationType>CIVILIZATION_BARBARIAN</CivilizationType>
			<BuildingClassType>BUILDINGCLASS_METEORA</BuildingClassType>
			<BuildingType/>
		</Row>
		<Row>
			<CivilizationType>CIVILIZATION_MINOR</CivilizationType>
			<BuildingClassType>BUILDINGCLASS_METEORA</BuildingClassType>
			<BuildingType/>
		</Row>
		<Row>
			<CivilizationType>CIVILIZATION_BARBARIAN</CivilizationType>
			<BuildingClassType>BUILDINGCLASS_PENA</BuildingClassType>
			<BuildingType/>
		</Row>
		<Row>
			<CivilizationType>CIVILIZATION_MINOR</CivilizationType>
			<BuildingClassType>BUILDINGCLASS_PENA</BuildingClassType>
			<BuildingType/>
		</Row>
		<Row>
			<CivilizationType>CIVILIZATION_BARBARIAN</CivilizationType>
			<BuildingClassType>BUILDINGCLASS_MADOL</BuildingClassType>
			<BuildingType/>
		</Row>
		<Row>
			<CivilizationType>CIVILIZATION_MINOR</CivilizationType>
			<BuildingClassType>BUILDINGCLASS_MADOL</BuildingClassType>
			<BuildingType/>
		</Row>
		<Row>
			<CivilizationType>CIVILIZATION_BARBARIAN</CivilizationType>
			<BuildingClassType>BUILDINGCLASS_LONDON</BuildingClassType>
			<BuildingType/>
		</Row>
		<Row>
			<CivilizationType>CIVILIZATION_MINOR</CivilizationType>
			<BuildingClassType>BUILDINGCLASS_LONDON</BuildingClassType>
			<BuildingType/>
		</Row>
		<Row>
			<CivilizationType>CIVILIZATION_BARBARIAN</CivilizationType>
			<BuildingClassType>BUILDINGCLASS_GATEWAY</BuildingClassType>
			<BuildingType/>
		</Row>
		<Row>
			<CivilizationType>CIVILIZATION_MINOR</CivilizationType>
			<BuildingClassType>BUILDINGCLASS_GATEWAY</BuildingClassType>
			<BuildingType/>
		</Row>
		<Row>
			<CivilizationType>CIVILIZATION_BARBARIAN</CivilizationType>
			<BuildingClassType>BUILDINGCLASS_SPUTNIK</BuildingClassType>
			<BuildingType/>
		</Row>
		<Row>
			<CivilizationType>CIVILIZATION_MINOR</CivilizationType>
			<BuildingClassType>BUILDINGCLASS_SPUTNIK</BuildingClassType>
			<BuildingType/>
		</Row>
		<Row>
			<CivilizationType>CIVILIZATION_BARBARIAN</CivilizationType>
			<BuildingClassType>BUILDINGCLASS_TOPKAPI</BuildingClassType>
			<BuildingType/>
		</Row>
		<Row>
			<CivilizationType>CIVILIZATION_MINOR</CivilizationType>
			<BuildingClassType>BUILDINGCLASS_TOPKAPI</BuildingClassType>
			<BuildingType/>
		</Row>
		<Row>
			<CivilizationType>CIVILIZATION_BARBARIAN</CivilizationType>
			<BuildingClassType>BUILDINGCLASS_WARTBURG</BuildingClassType>
			<BuildingType/>
		</Row>
		<Row>
			<CivilizationType>CIVILIZATION_MINOR</CivilizationType>
			<BuildingClassType>BUILDINGCLASS_WARTBURG</BuildingClassType>
			<BuildingType/>
		</Row>
		<Row>
			<CivilizationType>CIVILIZATION_BARBARIAN</CivilizationType>
			<BuildingClassType>BUILDINGCLASS_MESAVERDE</BuildingClassType>
			<BuildingType/>
		</Row>
		<Row>
			<CivilizationType>CIVILIZATION_MINOR</CivilizationType>
			<BuildingClassType>BUILDINGCLASS_MESAVERDE</BuildingClassType>
			<BuildingType/>
		</Row>
		<Row>
			<CivilizationType>CIVILIZATION_BARBARIAN</CivilizationType>
			<BuildingClassType>BUILDINGCLASS_TAJIN</BuildingClassType>
			<BuildingType/>
		</Row>
		<Row>
			<CivilizationType>CIVILIZATION_MINOR</CivilizationType>
			<BuildingClassType>BUILDINGCLASS_TAJIN</BuildingClassType>
			<BuildingType/>
		</Row>
		<Row>
			<CivilizationType>CIVILIZATION_BARBARIAN</CivilizationType>
			<BuildingClassType>BUILDINGCLASS_GOBEKLI</BuildingClassType>
			<BuildingType/>
		</Row>
		<Row>
			<CivilizationType>CIVILIZATION_MINOR</CivilizationType>
			<BuildingClassType>BUILDINGCLASS_GOBEKLI</BuildingClassType>
			<BuildingType/>
		</Row>
		<Row>
			<CivilizationType>CIVILIZATION_BARBARIAN</CivilizationType>
			<BuildingClassType>BUILDINGCLASS_BABEL</BuildingClassType>
			<BuildingType/>
		</Row>
		<Row>
			<CivilizationType>CIVILIZATION_MINOR</CivilizationType>
			<BuildingClassType>BUILDINGCLASS_BABEL</BuildingClassType>
			<BuildingType/>
		</Row>
		<Row>
			<CivilizationType>CIVILIZATION_BARBARIAN</CivilizationType>
			<BuildingClassType>BUILDINGCLASS_MILLAU</BuildingClassType>
			<BuildingType/>
		</Row>
		<Row>
			<CivilizationType>CIVILIZATION_MINOR</CivilizationType>
			<BuildingClassType>BUILDINGCLASS_MILLAU</BuildingClassType>
			<BuildingType/>
		</Row>
		<Row>
			<CivilizationType>CIVILIZATION_BARBARIAN</CivilizationType>
			<BuildingClassType>BUILDINGCLASS_DARJEELING</BuildingClassType>
			<BuildingType/>
		</Row>
		<Row>
			<CivilizationType>CIVILIZATION_MINOR</CivilizationType>
			<BuildingClassType>BUILDINGCLASS_DARJEELING</BuildingClassType>
			<BuildingType/>
		</Row>
		<Row>
			<CivilizationType>CIVILIZATION_BARBARIAN</CivilizationType>
			<BuildingClassType>BUILDINGCLASS_GRIPSHOLM</BuildingClassType>
			<BuildingType/>
		</Row>
		<Row>
			<CivilizationType>CIVILIZATION_MINOR</CivilizationType>
			<BuildingClassType>BUILDINGCLASS_GRIPSHOLM</BuildingClassType>
			<BuildingType/>
		</Row>
		<Row>
			<CivilizationType>CIVILIZATION_BARBARIAN</CivilizationType>
			<BuildingClassType>BUILDINGCLASS_ARECIBO</BuildingClassType>
			<BuildingType/>
		</Row>
		<Row>
			<CivilizationType>CIVILIZATION_MINOR</CivilizationType>
			<BuildingClassType>BUILDINGCLASS_ARECIBO</BuildingClassType>
			<BuildingType/>
		</Row>
		<Row>
			<CivilizationType>CIVILIZATION_BARBARIAN</CivilizationType>
			<BuildingClassType>BUILDINGCLASS_MLK</BuildingClassType>
			<BuildingType/>
		</Row>
		<Row>
			<CivilizationType>CIVILIZATION_MINOR</CivilizationType>
			<BuildingClassType>BUILDINGCLASS_MLK</BuildingClassType>
			<BuildingType/>
		</Row>
		<Row>
			<CivilizationType>CIVILIZATION_BARBARIAN</CivilizationType>
			<BuildingClassType>BUILDINGCLASS_WHITESANDS</BuildingClassType>
			<BuildingType/>
		</Row>
		<Row>
			<CivilizationType>CIVILIZATION_MINOR</CivilizationType>
			<BuildingClassType>BUILDINGCLASS_WHITESANDS</BuildingClassType>
			<BuildingType/>
		</Row>
		<Row>
			<CivilizationType>CIVILIZATION_BARBARIAN</CivilizationType>
			<BuildingClassType>BUILDINGCLASS_PANAMA</BuildingClassType>
			<BuildingType/>
		</Row>
		<Row>
			<CivilizationType>CIVILIZATION_MINOR</CivilizationType>
			<BuildingClassType>BUILDINGCLASS_PANAMA</BuildingClassType>
			<BuildingType/>
		</Row>
		<Row>
			<CivilizationType>CIVILIZATION_BARBARIAN</CivilizationType>
			<BuildingClassType>BUILDINGCLASS_TEMPLO</BuildingClassType>
			<BuildingType/>
		</Row>
		<Row>
			<CivilizationType>CIVILIZATION_MINOR</CivilizationType>
			<BuildingClassType>BUILDINGCLASS_TEMPLO</BuildingClassType>
			<BuildingType/>
		</Row>
		<Row>
			<CivilizationType>CIVILIZATION_BARBARIAN</CivilizationType>
			<BuildingClassType>BUILDINGCLASS_TOTEM</BuildingClassType>
			<BuildingType/>
		</Row>
		<Row>
			<CivilizationType>CIVILIZATION_MINOR</CivilizationType>
			<BuildingClassType>BUILDINGCLASS_TOTEM</BuildingClassType>
			<BuildingType/>
		</Row>
		<Row>
			<CivilizationType>CIVILIZATION_BARBARIAN</CivilizationType>
			<BuildingClassType>BUILDINGCLASS_TEOTIHUACAN</BuildingClassType>
			<BuildingType/>
		</Row>
		<Row>
			<CivilizationType>CIVILIZATION_MINOR</CivilizationType>
			<BuildingClassType>BUILDINGCLASS_TEOTIHUACAN</BuildingClassType>
			<BuildingType/>
		</Row>
		<Row>
			<CivilizationType>CIVILIZATION_BARBARIAN</CivilizationType>
			<BuildingClassType>BUILDINGCLASS_STONE_TOWN</BuildingClassType>
			<BuildingType/>
		</Row>
		<Row>
			<CivilizationType>CIVILIZATION_MINOR</CivilizationType>
			<BuildingClassType>BUILDINGCLASS_STONE_TOWN</BuildingClassType>
			<BuildingType/>
		</Row>
		<Row>
			<CivilizationType>CIVILIZATION_BARBARIAN</CivilizationType>
			<BuildingClassType>BUILDINGCLASS_ISHTAR</BuildingClassType>
			<BuildingType/>
		</Row>
		<Row>
			<CivilizationType>CIVILIZATION_MINOR</CivilizationType>
			<BuildingClassType>BUILDINGCLASS_ISHTAR</BuildingClassType>
			<BuildingType/>
		</Row>
		<Row>
			<CivilizationType>CIVILIZATION_BARBARIAN</CivilizationType>
			<BuildingClassType>BUILDINGCLASS_TITICACA</BuildingClassType>
			<BuildingType/>
		</Row>
		<Row>
			<CivilizationType>CIVILIZATION_MINOR</CivilizationType>
			<BuildingClassType>BUILDINGCLASS_TITICACA</BuildingClassType>
			<BuildingType/>
		</Row>
		<Row>
			<CivilizationType>CIVILIZATION_BARBARIAN</CivilizationType>
			<BuildingClassType>BUILDINGCLASS_TAHRIR</BuildingClassType>
			<BuildingType/>
		</Row>
		<Row>
			<CivilizationType>CIVILIZATION_MINOR</CivilizationType>
			<BuildingClassType>BUILDINGCLASS_TAHRIR</BuildingClassType>
			<BuildingType/>
		</Row>
		<Row>
			<CivilizationType>CIVILIZATION_BARBARIAN</CivilizationType>
			<BuildingClassType>BUILDINGCLASS_MARTYRS</BuildingClassType>
			<BuildingType/>
		</Row>
		<Row>
			<CivilizationType>CIVILIZATION_MINOR</CivilizationType>
			<BuildingClassType>BUILDINGCLASS_MARTYRS</BuildingClassType>
			<BuildingType/>
		</Row>
		<Row>
			<CivilizationType>CIVILIZATION_BARBARIAN</CivilizationType>
			<BuildingClassType>BUILDINGCLASS_PEARL_MONUMENT</BuildingClassType>
			<BuildingType/>
		</Row>
		<Row>
			<CivilizationType>CIVILIZATION_MINOR</CivilizationType>
			<BuildingClassType>BUILDINGCLASS_PEARL_MONUMENT</BuildingClassType>
			<BuildingType/>
		</Row>
		<Row>
			<CivilizationType>CIVILIZATION_BARBARIAN</CivilizationType>
			<BuildingClassType>BUILDINGCLASS_HABIB_BOURGUIBA</BuildingClassType>
			<BuildingType/>
		</Row>
		<Row>
			<CivilizationType>CIVILIZATION_MINOR</CivilizationType>
			<BuildingClassType>BUILDINGCLASS_HABIB_BOURGUIBA</BuildingClassType>
			<BuildingType/>
		</Row>
		<Row>
			<CivilizationType>CIVILIZATION_BARBARIAN</CivilizationType>
			<BuildingClassType>BUILDINGCLASS_SELARON</BuildingClassType>
			<BuildingType/>
		</Row>
		<Row>
			<CivilizationType>CIVILIZATION_MINOR</CivilizationType>
			<BuildingClassType>BUILDINGCLASS_SELARON</BuildingClassType>
			<BuildingType/>
		</Row>
		<Row>
			<CivilizationType>CIVILIZATION_BARBARIAN</CivilizationType>
			<BuildingClassType>BUILDINGCLASS_WATPHRAKAEW</BuildingClassType>
			<BuildingType/>
		</Row>
		<Row>
			<CivilizationType>CIVILIZATION_MINOR</CivilizationType>
			<BuildingClassType>BUILDINGCLASS_WATPHRAKAEW</BuildingClassType>
			<BuildingType/>
		</Row>
		<Row>
			<CivilizationType>CIVILIZATION_BARBARIAN</CivilizationType>
			<BuildingClassType>BUILDINGCLASS_YELLOW_CRANE</BuildingClassType>
			<BuildingType/>
		</Row>
		<Row>
			<CivilizationType>CIVILIZATION_MINOR</CivilizationType>
			<BuildingClassType>BUILDINGCLASS_YELLOW_CRANE</BuildingClassType>
			<BuildingType/>
		</Row>
		<Row>
			<CivilizationType>CIVILIZATION_BARBARIAN</CivilizationType>
			<BuildingClassType>BUILDINGCLASS_XUANKONG</BuildingClassType>
			<BuildingType/>
		</Row>
		<Row>
			<CivilizationType>CIVILIZATION_MINOR</CivilizationType>
			<BuildingClassType>BUILDINGCLASS_XUANKONG</BuildingClassType>
			<BuildingType/>
		</Row>
		<Row>
			<CivilizationType>CIVILIZATION_BARBARIAN</CivilizationType>
			<BuildingClassType>BUILDINGCLASS_SHANGHAI_WFC</BuildingClassType>
			<BuildingType/>
		</Row>
		<Row>
			<CivilizationType>CIVILIZATION_MINOR</CivilizationType>
			<BuildingClassType>BUILDINGCLASS_SHANGHAI_WFC</BuildingClassType>
			<BuildingType/>
		</Row>
		<Row>
			<CivilizationType>CIVILIZATION_BARBARIAN</CivilizationType>
			<BuildingClassType>BUILDINGCLASS_JIAYUGUAN</BuildingClassType>
			<BuildingType/>
		</Row>
		<Row>
			<CivilizationType>CIVILIZATION_MINOR</CivilizationType>
			<BuildingClassType>BUILDINGCLASS_JIAYUGUAN</BuildingClassType>
			<BuildingType/>
		</Row>
		<Row>
			<CivilizationType>CIVILIZATION_BARBARIAN</CivilizationType>
			<BuildingClassType>BUILDINGCLASS_GULOU</BuildingClassType>
			<BuildingType/>
		</Row>
		<Row>
			<CivilizationType>CIVILIZATION_MINOR</CivilizationType>
			<BuildingClassType>BUILDINGCLASS_GULOU</BuildingClassType>
			<BuildingType/>
		</Row>
		<Row>
			<CivilizationType>CIVILIZATION_BARBARIAN</CivilizationType>
			<BuildingClassType>BUILDINGCLASS_GATE_SUN</BuildingClassType>
			<BuildingType/>
		</Row>
		<Row>
			<CivilizationType>CIVILIZATION_MINOR</CivilizationType>
			<BuildingClassType>BUILDINGCLASS_GATE_SUN</BuildingClassType>
			<BuildingType/>
		</Row>
		<Row>
			<CivilizationType>CIVILIZATION_BARBARIAN</CivilizationType>
			<BuildingClassType>BUILDINGCLASS_KNOSSOS</BuildingClassType>
			<BuildingType/>
		</Row>
		<Row>
			<CivilizationType>CIVILIZATION_MINOR</CivilizationType>
			<BuildingClassType>BUILDINGCLASS_KNOSSOS</BuildingClassType>
			<BuildingType/>
		</Row>
		<Row>
			<CivilizationType>CIVILIZATION_BARBARIAN</CivilizationType>
			<BuildingClassType>BUILDINGCLASS_LALIBELA</BuildingClassType>
			<BuildingType/>
		</Row>
		<Row>
			<CivilizationType>CIVILIZATION_MINOR</CivilizationType>
			<BuildingClassType>BUILDINGCLASS_LALIBELA</BuildingClassType>
			<BuildingType/>
		</Row>
		<Row>
			<CivilizationType>CIVILIZATION_BARBARIAN</CivilizationType>
			<BuildingClassType>BUILDINGCLASS_TORRE</BuildingClassType>
			<BuildingType/>
		</Row>
		<Row>
			<CivilizationType>CIVILIZATION_MINOR</CivilizationType>
			<BuildingClassType>BUILDINGCLASS_TORRE</BuildingClassType>
			<BuildingType/>
		</Row>
		<Row>
			<CivilizationType>CIVILIZATION_BARBARIAN</CivilizationType>
			<BuildingClassType>BUILDINGCLASS_TAKTSANG</BuildingClassType>
			<BuildingType/>
		</Row>
		<Row>
			<CivilizationType>CIVILIZATION_MINOR</CivilizationType>
			<BuildingClassType>BUILDINGCLASS_TAKTSANG</BuildingClassType>
			<BuildingType/>
		</Row>
		<Row>
			<CivilizationType>CIVILIZATION_BARBARIAN</CivilizationType>
			<BuildingClassType>BUILDINGCLASS_LESHAN</BuildingClassType>
			<BuildingType/>
		</Row>
		<Row>
			<CivilizationType>CIVILIZATION_MINOR</CivilizationType>
			<BuildingClassType>BUILDINGCLASS_LESHAN</BuildingClassType>
			<BuildingType/>
		</Row>
		<Row>
			<CivilizationType>CIVILIZATION_BARBARIAN</CivilizationType>
			<BuildingClassType>BUILDINGCLASS_HANSA</BuildingClassType>
			<BuildingType/>
		</Row>
		<Row>
			<CivilizationType>CIVILIZATION_MINOR</CivilizationType>
			<BuildingClassType>BUILDINGCLASS_HANSA</BuildingClassType>
			<BuildingType/>
		</Row>
		<Row>
			<CivilizationType>CIVILIZATION_BARBARIAN</CivilizationType>
			<BuildingClassType>BUILDINGCLASS_BURJ_KHALIFA</BuildingClassType>
			<BuildingType/>
		</Row>
		<Row>
			<CivilizationType>CIVILIZATION_MINOR</CivilizationType>
			<BuildingClassType>BUILDINGCLASS_BURJ_KHALIFA</BuildingClassType>
			<BuildingType/>
		</Row>
		<Row>
			<CivilizationType>CIVILIZATION_BARBARIAN</CivilizationType>
			<BuildingClassType>BUILDINGCLASS_HELD</BuildingClassType>
			<BuildingType/>
		</Row>
		<Row>
			<CivilizationType>CIVILIZATION_MINOR</CivilizationType>
			<BuildingClassType>BUILDINGCLASS_HELD</BuildingClassType>
			<BuildingType/>
		</Row>
		<Row>
			<CivilizationType>CIVILIZATION_BARBARIAN</CivilizationType>
			<BuildingClassType>BUILDINGCLASS_OLLI</BuildingClassType>
			<BuildingType/>
		</Row>
		<Row>
			<CivilizationType>CIVILIZATION_MINOR</CivilizationType>
			<BuildingClassType>BUILDINGCLASS_OLLI</BuildingClassType>
			<BuildingType/>
		</Row>
		<Row>
			<CivilizationType>CIVILIZATION_BARBARIAN</CivilizationType>
			<BuildingClassType>BUILDINGCLASS_GGANTIJA</BuildingClassType>
			<BuildingType/>
		</Row>
		<Row>
			<CivilizationType>CIVILIZATION_MINOR</CivilizationType>
			<BuildingClassType>BUILDINGCLASS_GGANTIJA</BuildingClassType>
			<BuildingType/>
		</Row>
	</Civilization_BuildingClassOverrides>
  <!-- TODO: Insert table data example here.-->
  
  <!-- Enter your Game Data here. -->
  
</GameData>